{
  "date": "2026-05-19",
  "generated_at": "2026-05-19T22:55:29.995309",
  "articles": [
    {
      "title": "中国 上海で傷害事件 日本人2人けが 安全確保呼びかけ",
      "link": "https://news.web.nhk/newsweb/na/na-k10015126171000",
      "summary": "中国・上海のオフィスビルにある飲食店で19日、果物ナイフを持った男に襲われ日本人2人を含む3人がけがをし、病院で手当てを受けています。地元の警察が容疑者を拘束し事件のいきさつを調べています。",
      "published": "Wed, 20 May 2026 05:09:48 +0900",
      "label": "NHKトップ",
      "categories": [
        "general"
      ]
    },
    {
      "title": "日韓首脳 エネルギー供給強じん化で一致 政策対話で具体化へ",
      "link": "https://news.web.nhk/newsweb/na/na-k10015125951000",
      "summary": "高市総理大臣は19日、韓国のイ・ジェミョン(李在明)大統領と首脳会談を行い、インド太平洋地域での備蓄強化を含むエネルギー供給の強じん化を進めることなどで一致しました。今後、「政策対話」を立ち上げ、協力…",
      "published": "Wed, 20 May 2026 05:20:28 +0900",
      "label": "NHKトップ",
      "categories": [
        "general"
      ]
    },
    {
      "title": "きょう北京で中ロ首脳会談 両国の結束確認か",
      "link": "https://news.web.nhk/newsweb/na/na-k10015126001000",
      "summary": "中国の習近平国家主席とロシアのプーチン大統領が20日、中国の首都北京で会談し、欧米主導の国際秩序に対抗する姿勢を示すとともに、両国の結束を確認すると見られます。",
      "published": "Wed, 20 May 2026 05:33:43 +0900",
      "label": "NHKトップ",
      "categories": [
        "general"
      ]
    },
    {
      "title": "G7財務相・中銀総裁会議“世界経済にリスク AIモデルで協力”",
      "link": "https://news.web.nhk/newsweb/na/na-k10015126141000",
      "summary": "フランス・パリで開かれていたG7＝主要7か国の財務相・中央銀行総裁会議は、19日、閉幕し、イラン情勢を受けた世界経済のリスクの高まりや新たなAIモデルに関する情報共有の強化などを盛り込んだ共同声明が採…",
      "published": "Wed, 20 May 2026 06:14:04 +0900",
      "label": "NHKトップ",
      "categories": [
        "general"
      ]
    },
    {
      "title": "油井亀美也さん 子どもたちに宇宙の魅力語る 宇宙滞在報告会",
      "link": "https://news.web.nhk/newsweb/na/na-k10015125911000",
      "summary": "国際宇宙ステーションに長期滞在した宇宙飛行士の油井亀美也さんが子どもたちを対象にした報告会を都内で開き、「流れ星を宇宙から見ると地球に落ちていくように見えるので不思議です」などと宇宙のおもしろさを語り…",
      "published": "Tue, 19 May 2026 20:54:19 +0900",
      "label": "NHK経済",
      "categories": [
        "economy"
      ]
    },
    {
      "title": "米 バレエ 若手登竜門のコンクールで最優秀賞に佐居勇星さん",
      "link": "https://news.web.nhk/newsweb/na/na-k10015125211000",
      "summary": "若手バレエダンサーの登竜門として知られる「ユース・アメリカ・グランプリ」がアメリカ・テキサス州で開かれ、12歳から14歳の部門（1月1日時点）で、カリフォルニア州在住の佐居勇星さん（15）が最優秀賞に…",
      "published": "Tue, 19 May 2026 13:59:29 +0900",
      "label": "NHK経済",
      "categories": [
        "economy"
      ]
    },
    {
      "title": "「ミュトス」影響でセキュリティー会社に問い合わせ相次ぐ",
      "link": "https://news.web.nhk/newsweb/na/na-k10015124801000",
      "summary": "非常に高い性能で、サイバー攻撃に悪用された場合のリスクが指摘されている最新のAIモデル「クロード・ミュトス」について、都内のセキュリティー会社には、どの程度の影響があるかや対応方法について、企業からの…",
      "published": "Mon, 18 May 2026 18:07:26 +0900",
      "label": "NHK経済",
      "categories": [
        "economy"
      ]
    },
    {
      "title": "エボラ出血熱 「日本国内で広がる可能性は低い」 国の専門機関",
      "link": "https://news.web.nhk/newsweb/na/na-k10015124681000",
      "summary": "アフリカ中部のコンゴ民主共和国でエボラ出血熱の流行が起き、WHO＝世界保健機関が「国際的に懸念される公衆衛生上の緊急事態」を宣言したことについて、国立健康危機管理研究機構は18日、日本国内で広がる可能…",
      "published": "Mon, 18 May 2026 16:33:44 +0900",
      "label": "NHK経済",
      "categories": [
        "economy"
      ]
    },
    {
      "title": "将棋「名人戦」 藤井聡太六冠が4連勝で4連覇",
      "link": "https://news.web.nhk/newsweb/na/na-k10015124171000",
      "summary": "将棋の八大タイトルの1つ、「名人戦」七番勝負の第4局が大阪府で行われ、藤井聡太六冠（23）が挑戦者の糸谷哲郎九段（37）に勝って「名人」のタイトル4連覇を決めました。",
      "published": "Sun, 17 May 2026 21:07:14 +0900",
      "label": "NHK経済",
      "categories": [
        "economy"
      ]
    },
    {
      "title": "将棋「名人戦」 第4局始まる 藤井4連覇か 糸谷が望みつなぐか",
      "link": "https://news.web.nhk/newsweb/na/na-k10015123391000",
      "summary": "将棋の八大タイトルの1つ、「名人戦」の第4局が大阪府で始まり、藤井聡太六冠（23）が4連覇を決めるか、挑戦者の糸谷哲郎九段（37）がタイトル奪取に望みをつなぐか、注目されます。",
      "published": "Sat, 16 May 2026 20:05:55 +0900",
      "label": "NHK経済",
      "categories": [
        "economy"
      ]
    },
    {
      "title": "【地震】福島第一・第二原発 新たな異常確認されず 東京電力",
      "link": "https://news.web.nhk/newsweb/na/na-k10015123061000",
      "summary": "東京電力によりますと、福島県の大熊町と双葉町にある福島第一原子力発電所では、これまでのところ今回の地震による新たな異常は確認されていないということです。また、原発周辺の放射線量を測定するモニタリングポ…",
      "published": "Fri, 15 May 2026 21:17:49 +0900",
      "label": "NHK経済",
      "categories": [
        "economy"
      ]
    },
    {
      "title": "「名探偵コナン」毛利蘭役 声優の山崎和佳奈さん死去 61歳",
      "link": "https://news.web.nhk/newsweb/na/na-k10015122711000",
      "summary": "人気アニメ「名探偵コナン」のヒロイン毛利蘭や、「ひみつのアッコちゃん」の3代目アッコの声などを担当した声優の山崎和佳奈さんが、先月18日、病気のため亡くなりました。61歳でした。",
      "published": "Fri, 15 May 2026 17:01:46 +0900",
      "label": "NHK経済",
      "categories": [
        "economy"
      ]
    },
    {
      "title": "作家 佐藤愛子さん死去 102歳 「血脈」などの小説で知られる",
      "link": "https://news.web.nhk/newsweb/na/na-k10015122271000",
      "summary": "「血脈」や「戦いすんで日が暮れて」などの小説で知られ、90歳の本音をつづったエッセーがベストセラーにもなった作家の佐藤愛子さんが、先月29日に老衰のため亡くなりました。102歳でした。",
      "published": "Fri, 15 May 2026 16:53:11 +0900",
      "label": "NHK経済",
      "categories": [
        "economy"
      ]
    },
    {
      "title": "米高性能AIモデルの対策 来週18日に関係省庁会議開催へ",
      "link": "https://news.web.nhk/newsweb/na/na-k10015122521000",
      "summary": "アメリカの企業が開発した高性能なAIモデルによって、重要な社会基盤がサイバー攻撃を受けるリスクが指摘されていることを受けて、松本デジタル大臣は、来週、関係省庁の担当者を集めた会議を開き、できる対策から…",
      "published": "Fri, 15 May 2026 13:22:30 +0900",
      "label": "NHK経済",
      "categories": [
        "economy"
      ]
    },
    {
      "title": "美空ひばりさんの未発表曲見つかる 18歳の時にレコーディング",
      "link": "https://news.web.nhk/newsweb/na/na-k10015122261000",
      "summary": "国民的な歌手として親しまれた美空ひばりさんの未発表曲が見つかりました。今から70年前、18歳の時にレコーディングされ、叙情的なメロディーが特徴的だということで、専門家は「美空ひばりがあらゆるスタイルの…",
      "published": "Fri, 15 May 2026 12:13:21 +0900",
      "label": "NHK経済",
      "categories": [
        "economy"
      ]
    },
    {
      "title": "宇宙飛行士の若田光一さん 米宇宙開発企業の日本法人代表に",
      "link": "https://news.web.nhk/newsweb/na/na-k10015121931000",
      "summary": "2030年に運用を終える国際宇宙ステーションの後継機の開発に名乗りを上げているアメリカの民間企業が、新たに日本法人を設立することになり、宇宙飛行士の若田光一さんが代表を務めることになりました。",
      "published": "Thu, 14 May 2026 20:25:41 +0900",
      "label": "NHK経済",
      "categories": [
        "economy"
      ]
    },
    {
      "title": "コンビニ各社 プラスチック削減進める 中東情勢の対応で",
      "link": "https://news.web.nhk/newsweb/na/na-k10015125971000",
      "summary": "中東情勢の影響でプラスチック容器などの価格が値上がりしていることから、コンビニ大手の間では、紙の容器に見直したり、再利用の割合を増やしたりする動きが出始めています。",
      "published": "Wed, 20 May 2026 06:53:38 +0900",
      "label": "NHK社会",
      "categories": [
        "general"
      ]
    },
    {
      "title": "【動画】Pickup NEWS（5月20日）",
      "link": "https://news.web.nhk/newsweb/na/na-k10015125811000",
      "summary": "これまでに入っているニュースを、まとめて1分の動画でお伝えします。（データ放送では動画をご覧いただけません）",
      "published": "Wed, 20 May 2026 06:47:01 +0900",
      "label": "NHK社会",
      "categories": [
        "general"
      ]
    },
    {
      "title": "2度目の後発地震注意情報 防災行動取る人が減少 専門家調査",
      "link": "https://news.web.nhk/newsweb/na/na-k10015125921000",
      "summary": "4月20日の三陸沖の地震を受けて発表された「北海道・三陸沖後発地震注意情報」。2度目の発表となった今回、情報の対象地域で、避難場所の確認などの防災行動を取ったと答えた人は、去年初めて発表された時よりも…",
      "published": "Wed, 20 May 2026 05:07:35 +0900",
      "label": "NHK社会",
      "categories": [
        "general"
      ]
    },
    {
      "title": "全国の駅周辺再開発 7割で計画見直しなど 建設会社入札辞退も",
      "link": "https://news.web.nhk/newsweb/na/na-k10015125871000",
      "summary": "全国の駅周辺で計画された再開発事業についてNHKが100余りの自治体や企業にアンケート調査したところ、7割が事業費の増加や工期の延長などの計画の見直し、それに中止、中断を強いられたことがわかりました。…",
      "published": "Wed, 20 May 2026 05:05:46 +0900",
      "label": "NHK社会",
      "categories": [
        "general"
      ]
    },
    {
      "title": "旧統一教会清算手続き きょうから1年間 債権の申し出受け付け",
      "link": "https://news.web.nhk/newsweb/na/na-k10015125901000",
      "summary": "解散命令を受けた旧統一教会の清算手続きを進めている清算人は、20日から1年間、献金被害などの債権の申し出を受け付けます。清算人はこれまでに教団の資産として少なくとも400億円の預貯金を確保したとしてい…",
      "published": "Wed, 20 May 2026 04:58:05 +0900",
      "label": "NHK社会",
      "categories": [
        "general"
      ]
    },
    {
      "title": "【QA解説】給与から天引き「子ども・子育て支援金」とは？",
      "link": "https://news.web.nhk/newsweb/na/na-k10015126131000",
      "summary": "今年度から少子化対策として始まった「子ども・子育て支援金」。一部の人は、先月の給与から天引きが始まってますが、会社員などはこの5月の給与から徴収されます。どのような目的で、どのように少子化対策に使われ…",
      "published": "Tue, 19 May 2026 23:50:32 +0900",
      "label": "NHK社会",
      "categories": [
        "general"
      ]
    },
    {
      "title": "【動画】Pickup NEWS（5月19日）",
      "link": "https://news.web.nhk/newsweb/na/na-k10015124691000",
      "summary": "これまでに入っているニュースを、まとめて1分の動画でお伝えします。（データ放送では動画をご覧いただけません）",
      "published": "Tue, 19 May 2026 19:47:10 +0900",
      "label": "NHK社会",
      "categories": [
        "general"
      ]
    },
    {
      "title": "この夏も気温高い見込み 梅雨期は多雨のおそれ 気象庁",
      "link": "https://news.web.nhk/newsweb/na/na-k10015125441000",
      "summary": "気象庁が発表した3か月予報によりますと、6月から8月にかけての夏の天候は、全国的に平年よりも気温が高く、厳しい暑さとなる見込みです。気象庁は暑さへの対策を進めるとともに、梅雨の時期は平年より降水量が多…",
      "published": "Tue, 19 May 2026 19:31:34 +0900",
      "label": "NHK社会",
      "categories": [
        "general"
      ]
    },
    {
      "title": "「完全養殖」ウナギのかば焼き 初めて一般向け販売へ",
      "link": "https://news.web.nhk/newsweb/na/na-k10015125271000",
      "summary": "絶滅のおそれが指摘される二ホンウナギについて、国の研究機関が開発した技術を使って大分県の水産会社が卵から育てたいわゆる「完全養殖」のウナギが初めて一般向けに販売されることになりました。",
      "published": "Tue, 19 May 2026 19:21:51 +0900",
      "label": "NHK社会",
      "categories": [
        "general"
      ]
    },
    {
      "title": "上皇ご夫妻 神奈川 葉山で静養に",
      "link": "https://news.web.nhk/newsweb/na/na-k10015125331000",
      "summary": "上皇ご夫妻は、19日から神奈川県の葉山で静養に入られました。",
      "published": "Tue, 19 May 2026 19:01:29 +0900",
      "label": "NHK社会",
      "categories": [
        "general"
      ]
    },
    {
      "title": "中東情勢悪化でナフサ高騰 ビニール袋・トレー“包装資材”の仕入れ30％↑にスーパー悲鳴「今度は何が値上がりするのか」 - Yahoo!ニュース",
      "link": "https://news.google.com/rss/articles/CBMif0FVX3lxTE1nZUVyYTdjcmR5bG01Z0xDUFN3azg5Sk9CQi1hb1lON1BfcGRpUFRlOHk4ZnY2TnIxMm5rVXhZSTNFUy1uV2ZwYm5VeUYwbGl1bWM4RnV0cGNGWnZjNGtnRExPYi0zWnh4NDVUUk1TNFlfX1hXME1ERTBQeEFpbUk?oc=5",
      "summary": "中東情勢悪化でナフサ高騰 ビニール袋・トレー“包装資材”の仕入れ30％↑にスーパー悲鳴「今度は何が値上がりするのか」  Yahoo!ニュース",
      "published": "Tue, 12 May 2026 20:00:42 GMT",
      "label": "食材値上がり",
      "categories": [
        "cost"
      ]
    },
    {
      "title": "【税理士監修・2026年4月値上げ一覧】経営への影響は？ガソリン・食品・固定電話・社会保険料まで経営者が今すぐ打つべき対策 - sogyotecho.jp",
      "link": "https://news.google.com/rss/articles/CBMiS0FVX3lxTE1kcmNJUEZOck5qdmhvSFZHaElUaGo2Vi1TMTVjcFBheklWaG9Ic0p3Ylc5R21GdHFpVzR1T2FITlg1N3lyTU1XQXhRYw?oc=5",
      "summary": "【税理士監修・2026年4月値上げ一覧】経営への影響は？ガソリン・食品・固定電話・社会保険料まで経営者が今すぐ打つべき対策  sogyotecho.jp",
      "published": "Tue, 14 Apr 2026 07:00:00 GMT",
      "label": "食材値上がり",
      "categories": [
        "cost"
      ]
    },
    {
      "title": "“包装資材”値上げでスーパーから悲鳴　ビニール袋・トレーの仕入れ30％↑に「どんどん売りづらくなっている」 - ｄメニューニュース",
      "link": "https://news.google.com/rss/articles/CBMickFVX3lxTE10UHQ0X2dTSGZxdDNkVjFWSXRQVFFkWVNnU0UybXY5bGo0dm1CSDFsbDUzc0dhRmJIeDYteU5CYS1xVTQ4dHJBeEVENWFQYVdZdnNyaWt0SDE4R0RBV1dXNFhmU3hCeFZjY2xwcWN2UWoxZ9IBd0FVX3lxTFBUYU0wZElMdXhBZ2VNOFM1cFFlbVZRaU9WV0tXeGF6YnBRcDBuU3lCYmZzb1g2TEJ3ZDRIaXFxVnRSbkhXWWkzVWczRUlEY2RKNzc0U28zNWJfYllYS3FUUUdlOEdPVmdfdEhuR2x1RlhtM0J0NUVr?oc=5",
      "summary": "“包装資材”値上げでスーパーから悲鳴　ビニール袋・トレーの仕入れ30％↑に「どんどん売りづらくなっている」  ｄメニューニュース",
      "published": "Fri, 01 May 2026 17:08:25 GMT",
      "label": "食材値上がり",
      "categories": [
        "cost"
      ]
    },
    {
      "title": "中東情勢悪化でナフサ高騰　ビニール袋・トレー“包装資材”の仕入れ30％↑にスーパー悲鳴「今度は何が値上がりするのか」 | チバテレ＋プラス - 千葉テレビ放送株式会社",
      "link": "https://news.google.com/rss/articles/CBMiX0FVX3lxTE5QTlVVMXdWd09YTHd0UHA2Zk5yZkUzVThJSTFMNEdRdS1jSHBsTDZQYVk5U0dBT0psQzlxTXowWU4xVE1yRGw2S1IybjBDUkJJS3dWRUtjWFpFQWxtck9R0gFkQVVfeXFMT09wQnROUjBGYlMyUU1WbHQyaXNjWE9XOTJRSkdyZlJsdGZNcGdCVVVIU084dVpJcHBCS0xNYWE1LU9kRnFkYU5UWTN1ZkQ2cl9uMjluMWpnUWd0Y1N6NkMwbG5oeQ?oc=5",
      "summary": "中東情勢悪化でナフサ高騰　ビニール袋・トレー“包装資材”の仕入れ30％↑にスーパー悲鳴「今度は何が値上がりするのか」 | チバテレ＋プラス  千葉テレビ放送株式会社",
      "published": "Tue, 12 May 2026 20:04:30 GMT",
      "label": "食材値上がり",
      "categories": [
        "cost"
      ]
    },
    {
      "title": "食料品の消費税ゼロで一体何が起きる？ ― 飲食店とスーパーの違い ― - 選挙ドットコム",
      "link": "https://news.google.com/rss/articles/CBMiX0FVX3lxTE1kZTN5RmNveW1YVHpWQXFaWS1vMVFudFV5YmlUWGpjaEoySHhxdWh6UklXdFJ4SERaaWg3ZEplOXNmN1Naam1oVjVDWUxUc1BVQUdMMWl6dnNJa3pWbkZR?oc=5",
      "summary": "食料品の消費税ゼロで一体何が起きる？ ― 飲食店とスーパーの違い ―  選挙ドットコム",
      "published": "Mon, 19 Jan 2026 08:00:00 GMT",
      "label": "食材値上がり",
      "categories": [
        "cost"
      ]
    },
    {
      "title": "食料品消費税ゼロで飲食店経営はどう変わる？「仕入税額控除」から読み解く致命的なリスク | 飲食店ドットコム ジャーナル - 飲食店ドットコム",
      "link": "https://news.google.com/rss/articles/CBMiXEFVX3lxTE90XzVDU29VTHE5WlhfMVI1cl90QjhCNWpxZDdaN1U3dmE1WktmRzk1aEJobnpSWVkxZWZ3YWJtQTdKNjBwV0l5WnJ3UU1sN3Z6TGZoeXpTUkVNUzRF?oc=5",
      "summary": "食料品消費税ゼロで飲食店経営はどう変わる？「仕入税額控除」から読み解く致命的なリスク | 飲食店ドットコム ジャーナル  飲食店ドットコム",
      "published": "Thu, 29 Jan 2026 08:00:00 GMT",
      "label": "食材値上がり",
      "categories": [
        "cost"
      ]
    },
    {
      "title": "キャベツの仕入れ価格30円アップ 販売価格194円 生育の端境期で価格上昇 レタス価格は安定 - 愛知のニュース",
      "link": "https://news.google.com/rss/articles/CBMiWkFVX3lxTE5RcFBiN1d2U0JoeUdzeFF1aFliZ1JlUWczeExKTi1TNkpMdmpMTFB0TERCbjVIbFhVYWlfVU9IX1pFZlloTlEyZjZSN200ckdkVGV0ZzBITnVNdw?oc=5",
      "summary": "キャベツの仕入れ価格30円アップ 販売価格194円 生育の端境期で価格上昇 レタス価格は安定  愛知のニュース",
      "published": "Wed, 08 Apr 2026 07:00:00 GMT",
      "label": "食材値上がり",
      "categories": [
        "cost"
      ]
    },
    {
      "title": "「食料品消費税ゼロ」で飲食店が倒産危機？問題は\"値下げしない\"か\"内容量を減らす\"こと - 寺田税理士･社会保険労務士事務所",
      "link": "https://news.google.com/rss/articles/CBMiY0FVX3lxTE9xWldNWV85U2h0ZDJPdURZeEV5LXhhbDUxSC14U2phaGxxMHBpMzhlSGw4a21VdFd1bjlkZndCS0gyQ2U4MGZtX0NucEpuQzNpSGo0dUx5NXJTcG5NV29qWHdGOA?oc=5",
      "summary": "「食料品消費税ゼロ」で飲食店が倒産危機？問題は\"値下げしない\"か\"内容量を減らす\"こと  寺田税理士･社会保険労務士事務所",
      "published": "Sat, 24 Jan 2026 08:00:00 GMT",
      "label": "食材値上がり",
      "categories": [
        "cost"
      ]
    },
    {
      "title": "「もう成り立たない」100円ショップ危機 仕入れ値次々上昇 製造業者も「正直赤字」 - テレ朝NEWS",
      "link": "https://news.google.com/rss/articles/CBMickFVX3lxTE95NVk3Vm5yQmQybmlYNlZWR0l2cVJPVE92UHlfWm44WGtGdFphYlQwbnJZSHFlaS1hdy1zMGo0eWE0bEJQaEJyYVBEMTZkNFZlLUtndmdiRnViVHdYZUp2VlBLMzVPZ0hqY25JbHZTc2pzdw?oc=5",
      "summary": "「もう成り立たない」100円ショップ危機 仕入れ値次々上昇 製造業者も「正直赤字」  テレ朝NEWS",
      "published": "Fri, 26 Dec 2025 08:00:00 GMT",
      "label": "食材値上がり",
      "categories": [
        "cost"
      ]
    },
    {
      "title": "【寄稿】食料品ゼロ税率はなぜダメなのか 元静岡大学教授・税理士 湖東京至 - 長周新聞",
      "link": "https://news.google.com/rss/articles/CBMiW0FVX3lxTFBJc2FHaXRvVTlsOS05OTBFVFcwelkydmczUUt4elJudFdpRGRHY09BQThHUEU3cHlvdEZ6aFJSLS1uM1NXUHR3TDhreTdqOW1LdXl6VllBVGJSb1k?oc=5",
      "summary": "【寄稿】食料品ゼロ税率はなぜダメなのか 元静岡大学教授・税理士 湖東京至  長周新聞",
      "published": "Fri, 18 Jul 2025 07:00:00 GMT",
      "label": "食材値上がり",
      "categories": [
        "cost"
      ]
    },
    {
      "title": "円安の抑制で日銀が為替介入 - komei.or.jp",
      "link": "https://news.google.com/rss/articles/CBMikAJBVV95cUxQajZ5X2libV80d3BiQ3VjaGFEUlFPRE9XRnBjbGdLMEpROFM1aGs1M2Y4U1hHRlhOQ2hLb2MxczVSaGx4MHZ5V294Q2FwSXc5NVpNekNJVmIydHU1dVBURU9ITjVoSzYxWC1YVnZTekFoOUZOd09sWmsxejgwNGNoSHlCU3Q2ZTZXWjh4b3U5TjZXTGpaSGR6TE8tNkl4RktOUGtBcXM4U2diS0RyZ0hUTFNxbl8zWjU5MjZFMFJuYkhkSlFrZmpSRXBOWkVkR3N5OWJwb01RdU9CMU5aM1drcWhFb1l6V19BMzY4Zzc2NWN1bUVrR3c4dkljRTl0bkN3UkpwN1lPSUFnV3EyeFl0cg?oc=5",
      "summary": "円安の抑制で日銀が為替介入  komei.or.jp",
      "published": "Sat, 16 May 2026 21:07:36 GMT",
      "label": "為替・輸入コスト",
      "categories": [
        "cost",
        "economy"
      ]
    },
    {
      "title": "(クローズアップNOW)円安の抑制で日銀が為替介入 4、5月で10兆円規模か 円大幅高、一時150円台半ば 2026.5.17付 - 公明新聞電子版プラス",
      "link": "https://news.google.com/rss/articles/CBMibkFVX3lxTFBSeHM5cEhEY1cyWVlxMFRscEtZaWt6T1AxZ2p4VlBhZktUSDJTaEJxSHJXVUxDTjA0M2tQNkR6MUExUWFqYTlNWnRMeVFackRwTHZNdG9QYnJER1Y3TlVhenFfQWFyS2dpVlczdXZn?oc=5",
      "summary": "(クローズアップNOW)円安の抑制で日銀が為替介入 4、5月で10兆円規模か 円大幅高、一時150円台半ば 2026.5.17付  公明新聞電子版プラス",
      "published": "Sat, 16 May 2026 20:01:17 GMT",
      "label": "為替・輸入コスト",
      "categories": [
        "cost",
        "economy"
      ]
    },
    {
      "title": "再び忍び寄る円安インフレの足音、円建ての輸入物価は2024年7月以来の伸びに、インフレ圧力は国内物価に波及必至 【唐鎌大輔の為替から見る日本】4月会合では利上げ見送りの公算だが、6月、7月会合に向けた地ならしは進むか(1/3) - JBpress",
      "link": "https://news.google.com/rss/articles/CBMiVkFVX3lxTE9XY0VyZ3l1OERXTWN1bmg2b2xzUzhiTlJJN3lfT1ZkbjM5aU5aUE5aTVNnZ3VtUUc2ejhjdU9qZDQ0bUp4cTkwZlFqOVZxUUFrYXk5VVhB?oc=5",
      "summary": "再び忍び寄る円安インフレの足音、円建ての輸入物価は2024年7月以来の伸びに、インフレ圧力は国内物価に波及必至 【唐鎌大輔の為替から見る日本】4月会合では利上げ見送りの公算だが、6月、7月会合に向けた地ならしは進むか(1/3)  JBpress",
      "published": "Sat, 25 Apr 2026 07:00:00 GMT",
      "label": "為替・輸入コスト",
      "categories": [
        "cost",
        "economy"
      ]
    },
    {
      "title": "【社説】政府の為替介入 円安構造に改善のメスを - 西日本新聞me",
      "link": "https://news.google.com/rss/articles/CBMiVkFVX3lxTE1iSFBYYXRkMFJsa0lGN1UwY2RNU3A4ekVtbUVIczhEckVoMDE3eTBWY0VBTDFVRUZnS1ZKSWdkbkVLOHhYOUsxZTZhY1JlU09vZWRJb2Fn?oc=5",
      "summary": "【社説】政府の為替介入 円安構造に改善のメスを  西日本新聞me",
      "published": "Wed, 13 May 2026 21:00:00 GMT",
      "label": "為替・輸入コスト",
      "categories": [
        "cost",
        "economy"
      ]
    },
    {
      "title": "まもなく米小売売上高、米輸入物価指数などの発表 - みんかぶ FX/為替",
      "link": "https://news.google.com/rss/articles/CBMiSEFVX3lxTE1wSjhoOVI0QzU3eTNvQXczYXpKaXE1VlFxVFplR09lMTlHYTZad1prWEw2WVhaZm9HZjJJem1Lb2ZLeXNkQWJaQQ?oc=5",
      "summary": "まもなく米小売売上高、米輸入物価指数などの発表  みんかぶ FX/為替",
      "published": "Thu, 14 May 2026 12:10:40 GMT",
      "label": "為替・輸入コスト",
      "categories": [
        "cost",
        "economy"
      ]
    },
    {
      "title": "【市場概況】東京為替見通し＝ドル円、12月輸入物価指数をまず確認 その後は円買い介入の可能性に要警戒か - 外為どっとコム",
      "link": "https://news.google.com/rss/articles/CBMiY0FVX3lxTFBhSld3b3BTbnVobWRjN3kyRnlxUnZHUWNqUkJCYmF4YklPUHBnTFoxUy1oLTV0TFhuSEpVOS0wOFBoMncwVDJHa0dPMGFxdWNFVFEzNEVDV3pwMFhLRndvRk1KOA?oc=5",
      "summary": "【市場概況】東京為替見通し＝ドル円、12月輸入物価指数をまず確認 その後は円買い介入の可能性に要警戒か  外為どっとコム",
      "published": "Thu, 15 Jan 2026 08:00:00 GMT",
      "label": "為替・輸入コスト",
      "categories": [
        "cost",
        "economy"
      ]
    },
    {
      "title": "円安ショック後の物価押し上げ、近年は大きくなっている＝日銀展望リポート - ロイター",
      "link": "https://news.google.com/rss/articles/CBMieEFVX3lxTE03eVhhWWVabGVIYmliTzloQ0I5YXNoNnRieGt2MVhleWM2UF9ZZ3dSXzJRLWtVbEZPclJDVFpDSGZyYlRLY29KVnkyeG5tZkwyeVJtVXRtSG8zRFM5YlIyQmZjeVVjOHZxQVNZZ3ZTNTU3SUg0dVJzUA?oc=5",
      "summary": "円安ショック後の物価押し上げ、近年は大きくなっている＝日銀展望リポート  ロイター",
      "published": "Sun, 25 Jan 2026 08:00:00 GMT",
      "label": "為替・輸入コスト",
      "categories": [
        "cost",
        "economy"
      ]
    },
    {
      "title": "「金融緩和で景気下支え」は過去 円安足かせ 日銀のジレンマ - 毎日新聞",
      "link": "https://news.google.com/rss/articles/CBMif0FVX3lxTFBfU1BKWmg0YmZGXzlHMEFkNS1ZZkZvVThkcno3b0RZTFJrdWtjZUNvdUlwOFBwY3BqQmZvU3pJbnc0YmJkLU9jdWNpX3htTW5yNHkwdTNHTXUweG55emtzMTNMd3ZuLTR6S09BX2J1ai14LXZrSnRFNjA3ZHRRM1k?oc=5",
      "summary": "「金融緩和で景気下支え」は過去 円安足かせ 日銀のジレンマ  毎日新聞",
      "published": "Fri, 01 May 2026 07:00:00 GMT",
      "label": "為替・輸入コスト",
      "categories": [
        "cost",
        "economy"
      ]
    },
    {
      "title": "2025年度の最低賃金改定について独自調査。飲食店での人件費高騰への具体的な対策は？ - 飲食店ドットコム",
      "link": "https://news.google.com/rss/articles/CBMiXEFVX3lxTE12VmtwU2NFTFFFbzdDRUVrSXptVmgzTDlESjc0djhhT2dxckgyYWJZQ3JzSE5HUzhUMTdlMGszd3BvNW50cFA3YXdTMXpkbEttVmY3bXVtQl91TmVH?oc=5",
      "summary": "2025年度の最低賃金改定について独自調査。飲食店での人件費高騰への具体的な対策は？  飲食店ドットコム",
      "published": "Wed, 24 Sep 2025 07:00:00 GMT",
      "label": "人件費・労働",
      "categories": [
        "labor"
      ]
    },
    {
      "title": "15％が、経営継続が危ういと回答～飲食店の2025最低賃金調査～ - PR TIMES",
      "link": "https://news.google.com/rss/articles/CBMiakFVX3lxTE1ZYXhSbExuU0R2SjVWa3ZHNU9wVjlzbnF4eGxxS2Nxd2l6c0FMVnh3a2p1SWFvVjNlOERpaFBTX2VfRlNZeUVHR09kc042aUYtWDdHem9aM1c3RThhMF92WVRhOGdISXlzeHc?oc=5",
      "summary": "15％が、経営継続が危ういと回答～飲食店の2025最低賃金調査～  PR TIMES",
      "published": "Fri, 26 Sep 2025 07:00:00 GMT",
      "label": "人件費・労働",
      "categories": [
        "labor"
      ]
    },
    {
      "title": "2025年度上期、飲食業界の平均給与が上昇。東京は月給30万円台へ | 飲食店ドットコム ジャーナル - 飲食店ドットコム",
      "link": "https://news.google.com/rss/articles/CBMiXEFVX3lxTE1oYTc2cDNCT2dGcWpMbXhteko0WUFvMGVXUUVNS0hadEJyMmlTQ0VnZkphcGpYN1d0alhIRFBhaU55Ym9palF2WDVRUkl1UnBaSHRlZktoSTRDWmhS?oc=5",
      "summary": "2025年度上期、飲食業界の平均給与が上昇。東京は月給30万円台へ | 飲食店ドットコム ジャーナル  飲食店ドットコム",
      "published": "Thu, 13 Nov 2025 08:00:00 GMT",
      "label": "人件費・労働",
      "categories": [
        "labor"
      ]
    },
    {
      "title": "飲食店の“人手不足倒産”を止める切り札…ロボットと冷凍テクノロジーで経営が激変 - ビジネスジャーナル",
      "link": "https://news.google.com/rss/articles/CBMiW0FVX3lxTE9mYnVETW9RUVRnbGIyM0t6OWVRd3h2SlhFQUFlMVY3QWRsekEweEZkVjVVM1RIOGhFd0NXaTVmRGU3azIxZTA4dGxTbDJLYVNwQVhxX0hVdjFPZnM?oc=5",
      "summary": "飲食店の“人手不足倒産”を止める切り札…ロボットと冷凍テクノロジーで経営が激変  ビジネスジャーナル",
      "published": "Thu, 04 Dec 2025 08:00:00 GMT",
      "label": "人件費・労働",
      "categories": [
        "labor"
      ]
    },
    {
      "title": "働く側はうれしいけど...最低賃金1121円で危機に陥る「雇う側」の現実 利益が吹っ飛んだ激安スーパー、倒産続出の製造業、人手の奪い合いに負け続ける飲食店 - ライブドアニュース",
      "link": "https://news.google.com/rss/articles/CBMiX0FVX3lxTE1oTVBfclN5aGxZUFpXUXZNYnVXZTZLaTFtT1BpZWdHX3FJakE2REh3UTFRVno3VnQ4aFVFZmo4OHpmX3ctN005S3B4S0h3TWpBbGFQZ3RxcjNMMkxNTjFJ?oc=5",
      "summary": "働く側はうれしいけど...最低賃金1121円で危機に陥る「雇う側」の現実 利益が吹っ飛んだ激安スーパー、倒産続出の製造業、人手の奪い合いに負け続ける飲食店  ライブドアニュース",
      "published": "Fri, 28 Nov 2025 08:00:00 GMT",
      "label": "人件費・労働",
      "categories": [
        "labor"
      ]
    },
    {
      "title": "全国15,248件から見る、物価高・人手不足の時代、飲食店出店はどう変わったのか - PR TIMES",
      "link": "https://news.google.com/rss/articles/CBMiakFVX3lxTE1FNXM2c2l3UXF4bGIyWlE5eUZFSEt0WFRvZ1BaT2lkeEpVMmNvcHR0eW1ZQUNrTFNrbTc5RDdNWC1qWWVZYnd1ZVJGZFFORVEwd3lsUmw0eUFZWWVWSEkxNi1oRmdvSjhOcXc?oc=5",
      "summary": "全国15,248件から見る、物価高・人手不足の時代、飲食店出店はどう変わったのか  PR TIMES",
      "published": "Thu, 05 Feb 2026 08:00:00 GMT",
      "label": "人件費・労働",
      "categories": [
        "labor"
      ]
    },
    {
      "title": "人手不足の飲食店、時給の目安は最低賃金プラス何%？ - Forbes JAPAN",
      "link": "https://news.google.com/rss/articles/CBMiWEFVX3lxTE5yWDhWZmRlOGlya2RBZ0pqOHhKQms3SUNDdjdXdmRYYXNUZ0lFY0xFcGNoNEw3QmtPcnNsbU1iLUFMLWRKbG92Z2dZcW1Bb1hCZlE5RjNLYUI?oc=5",
      "summary": "人手不足の飲食店、時給の目安は最低賃金プラス何%？  Forbes JAPAN",
      "published": "Tue, 07 Jan 2025 08:00:00 GMT",
      "label": "人件費・労働",
      "categories": [
        "labor"
      ]
    },
    {
      "title": "いくらなら人が来ますか？「理想は1200円」 人材獲得競争が熾烈な飲食業界 最低賃金だけではアルバイトは来ない - TBS NEWS DIG",
      "link": "https://news.google.com/rss/articles/CBMiV0FVX3lxTE91bTBGR01lNGhiQmFsaVZ1a0RGTXpLd0o2VFhXS3NyVDVieTQ1NGxtR0VCS1B4eUdJclkxT2N2T2NXUmlfdjZNb0xiWnNfS0FuWDI5bWp6cw?oc=5",
      "summary": "いくらなら人が来ますか？「理想は1200円」 人材獲得競争が熾烈な飲食業界 最低賃金だけではアルバイトは来ない  TBS NEWS DIG",
      "published": "Thu, 03 Oct 2024 07:00:00 GMT",
      "label": "人件費・労働",
      "categories": [
        "labor"
      ]
    },
    {
      "title": "外食業界「消費税ゼロ」に反対 来店客離れで経営に打撃（共同通信） - Yahoo!ニュース",
      "link": "https://news.google.com/rss/articles/CBMif0FVX3lxTFBoa045RTVLYzhuMzg3WVpxVVgzb3ZkVjdJT09kMWpuWEdCRVByOG9yS0pYUzAxTXlVU0tMNnpxaVc1YUIwNGVEclVRcDNLckc0Q19ZQlRJWU04NXpaMjd1cGF1TW5GUy1uckdsTV9USWVhMnhKRkkyZElvTDliWEE?oc=5",
      "summary": "外食業界「消費税ゼロ」に反対 来店客離れで経営に打撃（共同通信）  Yahoo!ニュース",
      "published": "Wed, 25 Feb 2026 08:00:00 GMT",
      "label": "外食・消費動向",
      "categories": [
        "consumer"
      ]
    },
    {
      "title": "食料品の消費税ゼロ、外食業界「客流れる」と不安 高市首相の答えは - 朝日新聞",
      "link": "https://news.google.com/rss/articles/CBMiZ0FVX3lxTFBkSmVDWHVRRnpOdk5VWk53blFZTnI5NkdoaEg5Z1dCMXlqRDNtc21VZS01bVgwZm05dXlPQ0pHZUx0MVJzRm85c1FIZmJ0SWZnTDdZWnlGYTBJUTdtYklMS3lVbnlCZVk?oc=5",
      "summary": "食料品の消費税ゼロ、外食業界「客流れる」と不安 高市首相の答えは  朝日新聞",
      "published": "Fri, 30 Jan 2026 08:00:00 GMT",
      "label": "外食・消費動向",
      "categories": [
        "consumer"
      ]
    },
    {
      "title": "外食業界「消費税ゼロ」に反対 来店客離れで経営に打撃 - nippon.com",
      "link": "https://news.google.com/rss/articles/CBMiY0FVX3lxTFA3TWpKdnVvUGVTVVhTc2RNb3ZZMWZGLXk4T1hnLU5lZXhySXB6cWdldVZGQmVkdjBKNElzZlk4Qzc3Y05hSGlVaGptSmZ1NEVNMkV6dklwREYyT1JZNXhPZHpHMA?oc=5",
      "summary": "外食業界「消費税ゼロ」に反対 来店客離れで経営に打撃  nippon.com",
      "published": "Wed, 25 Feb 2026 08:00:00 GMT",
      "label": "外食・消費動向",
      "categories": [
        "consumer"
      ]
    },
    {
      "title": "「飲食店の客離れを招く」食料品の消費税減税に懸念表明 日本フードサービス協会 - TBS NEWS DIG",
      "link": "https://news.google.com/rss/articles/CBMidEFVX3lxTE9hdi1RcFZ6LW1lVUlSN21sUFhRY1ZQbGY5eFJBMng4blU4eW9ydWp0cEJzUi1VSjNUaHQxQmhpQ2xvVi1EckJEZm1UX2dEeDNBWWVWU25uSXhDWU42azhFNTRGMXg1NXFsQTRhZWE5WGtCa2Nj?oc=5",
      "summary": "「飲食店の客離れを招く」食料品の消費税減税に懸念表明 日本フードサービス協会  TBS NEWS DIG",
      "published": "Wed, 25 Feb 2026 08:00:00 GMT",
      "label": "外食・消費動向",
      "categories": [
        "consumer"
      ]
    },
    {
      "title": "低価格路線のサイゼリヤは客数を増やしているが…外食を利用する消費者の財布が限界を超えつつある過酷な現実 - 東洋経済オンライン",
      "link": "https://news.google.com/rss/articles/CBMiX0FVX3lxTE5RQ0JWTmdxcEtiXzRKS2Y3b1RuYVBwSUNYVmVmZThNWjhjUFcwdlF5ZzdNVjNjNTBjS0tDTEp6b2tVS2xfZDBieGJyb242MjBfdVFIVFdmVndsMkM4MmJF?oc=5",
      "summary": "低価格路線のサイゼリヤは客数を増やしているが…外食を利用する消費者の財布が限界を超えつつある過酷な現実  東洋経済オンライン",
      "published": "Sat, 13 Sep 2025 07:00:00 GMT",
      "label": "外食・消費動向",
      "categories": [
        "consumer"
      ]
    },
    {
      "title": "「食料品消費税ゼロになると客が来なくなる」居酒屋店が悲鳴…減税で分かれる業界の明暗 - スマートニュース",
      "link": "https://news.google.com/rss/articles/CBMi1wRBVV95cUxPeE1SMmpPbWdlcWpYUTJzZVp4V29JNU5POFRDTWtOTzFGVGZFX3lpMVhSR05mTDRXQUNyRUxnUXlTRWlybk1JUWN2c1FKOVhYSTYyNVM4MHpJRTZjSmRkMElvOGhadTBhSlh6Q2Y2Rk14Z2F6MEh4NlNaVWh5TVpFamc3a3Q5REJpZVJpYW5Dc0U2MnNwV3hEQ3VrT3lNWXJESGNhSVI2QkRkV2E1T2FEVXBnVGlPSWtNc2o3TzZOM2loS3dmaC1KZFNvU0hBcERiOG5ibmd4azVjWVV5QlpnV1lsRHRCSVdybDZCclpUR0x1M3JpLWkyeFcwN0JfeFNncnoxeFAzQkxUSlNKSkJVaXdDM2U2N3NFZEN3MFNLMlREUGQ3NkRJV0xaU20tVWp3cVJwRzROQWU5N2RKNDY0MkN3RHZZOUpNSXBROVJtNjZGZTFzRlhVdFBFWVYtVHc0VnpQcVBjbS12eG5OcUZwMExZaVRXVDgwaHZHLWZyMktUd08xamZGbUNMazFjZUl3MUlQVlhuVTJUWUNJRHQwbTJMYmVMWXRtQmNzM1VfU0R3XzVzR3VZOGFNRlFuQmpPazZma2J4T3B1MjBtRWk1ODNncFFOZDhOelZ4endQQmF2SUV6aGE0aGdyNDZ3NUtkVzlqbXRlNmVpNlIybUxkWHVKS2l5d3Z2WktXc3AweWtBUG4yMkhYMmsxOXdhdk9UZE1LdDViR2plRTJyZ3NpNGRuMWo5Q1l5RlVaUzlybW9XZ2I0WUJVY0lNSklhc3N5a213c0NCbw?oc=5",
      "summary": "「食料品消費税ゼロになると客が来なくなる」居酒屋店が悲鳴…減税で分かれる業界の明暗  スマートニュース",
      "published": "Sun, 01 Mar 2026 08:00:00 GMT",
      "label": "外食・消費動向",
      "categories": [
        "consumer"
      ]
    },
    {
      "title": "外食業界「消費税ゼロ」に反対 来店客離れで経営に打撃 - 北海道新聞デジタル",
      "link": "https://news.google.com/rss/articles/CBMiWkFVX3lxTFBYWHJEMXYyYW1BcXQ4QXZkSUI4X1Z5eUZaZWNSaU1CNlUyeWV6UEN5eVljeUwtdGpoOE9xMlZjbTFJOS1najlIcU5zTDF6cTE3TEdoU0lqZXlUZw?oc=5",
      "summary": "外食業界「消費税ゼロ」に反対 来店客離れで経営に打撃  北海道新聞デジタル",
      "published": "Wed, 25 Feb 2026 08:00:00 GMT",
      "label": "外食・消費動向",
      "categories": [
        "consumer"
      ]
    },
    {
      "title": "外食 25年の全店売上高7.3％増 単価上昇が貢献、客数は頭打ち感も JF調査 - 食品新聞 WEB版",
      "link": "https://news.google.com/rss/articles/CBMiZEFVX3lxTE1xeUtYc3QwX1FrbjVPV3ZFS3dqcjJLdlVtNVV1QUJ6S0ZVVUhvdUNLb09kRTY4c3JyWHVyNC13QzI0UHVzNy1xVXhCcHh4eXpETFNyUlZLQzFabUJxOVR4OWQ3OVc?oc=5",
      "summary": "外食 25年の全店売上高7.3％増 単価上昇が貢献、客数は頭打ち感も JF調査  食品新聞 WEB版",
      "published": "Fri, 13 Feb 2026 08:00:00 GMT",
      "label": "外食・消費動向",
      "categories": [
        "consumer"
      ]
    },
    {
      "title": "外食業界「消費税ゼロ」に反対 来店客離れで経営に打撃 - kochinews.co.jp",
      "link": "https://news.google.com/rss/articles/CBMiXkFVX3lxTE02d0FJQnZGT3VKOWY3M2xFQkl0ZGF2V0xYaUpCMW45ZlA4eG1kVmZYR3I1MTQ1d2dpQW9FYUM0TWhqV2o0YS1qaWpQaVBVRWNoOVhzVjlyNmE1WlkyeGc?oc=5",
      "summary": "外食業界「消費税ゼロ」に反対 来店客離れで経営に打撃  kochinews.co.jp",
      "published": "Wed, 25 Feb 2026 08:00:00 GMT",
      "label": "外食・消費動向",
      "categories": [
        "consumer"
      ]
    },
    {
      "title": "外食業界「消費税ゼロ」に反対 - 京都新聞デジタル",
      "link": "https://news.google.com/rss/articles/CBMiW0FVX3lxTFB1MEVkZVNCUmo3RGc1VGhDVWVMUFh1aXhJWlRqXzdZeGhSMURaMHhDMHNkMzJoUUxnYTZOSk9Nc1pTbTl3NnpxM2I5VUZRbjNjdHBZbGJYVnE2TVE?oc=5",
      "summary": "外食業界「消費税ゼロ」に反対  京都新聞デジタル",
      "published": "Wed, 25 Feb 2026 08:00:00 GMT",
      "label": "外食・消費動向",
      "categories": [
        "consumer"
      ]
    },
    {
      "title": "25年度のラーメン店倒産、過去2番目に多い57件 物価高で - 日本経済新聞",
      "link": "https://news.google.com/rss/articles/CBMibEFVX3lxTE9jMmY5N3g3ODBsVzBncmo5dmJwRGUyWmRvTDgtbzNXT055emN2TzE1dnFHVjU3R2Rybk50R1BXWnl1RE9fd2F5bjVMLUJCdnJBay0zVkc3RURzNGZ2UnNVMDNnZUxuOGhzZktRcw?oc=5",
      "summary": "25年度のラーメン店倒産、過去2番目に多い57件 物価高で  日本経済新聞",
      "published": "Wed, 08 Apr 2026 07:00:00 GMT",
      "label": "ラーメン・飲食",
      "categories": [
        "restaurant"
      ]
    },
    {
      "title": "「値上げすれば客離れ、しなければ倒産」 飲食店を追い詰める「価格転嫁率32.3%」の現実 #エキスパートトピ - Yahoo!ニュース",
      "link": "https://news.google.com/rss/articles/CBMiiAFBVV95cUxNeWN0ZW5qLV8wVXJVVlk2SHJBT1ZtT3lfLUR1NDQzZmwyRXI2LS1TUV9Odms2Qy1RTUZXcVVkb1VuUHdzZnVvd0JLbkpRUHktcldzSnhkalFidkhQVWM1WUJnS3IwbkxsTWVOcHA2OHdmZEhvLThFeHAwTTUyTTVCWFFoQTlQblhV?oc=5",
      "summary": "「値上げすれば客離れ、しなければ倒産」 飲食店を追い詰める「価格転嫁率32.3%」の現実 #エキスパートトピ  Yahoo!ニュース",
      "published": "Sat, 17 Jan 2026 08:00:00 GMT",
      "label": "ラーメン・飲食",
      "categories": [
        "restaurant"
      ]
    },
    {
      "title": "2025年度の「ラーメン店」倒産は2番目 人手不足や値上げが影響 (2026年4月8日掲載) - ライブドアニュース",
      "link": "https://news.google.com/rss/articles/CBMiXkFVX3lxTFB3YldRMXlISEhWcnE3dm5QOWRLZS1mMGdXZ21yMTl4em8wMnZMQzdWcGRrTVhkOUtEMlBFNXNwOXZ3aW9FVTRVMDUtbW9mUGNYT2s0Q3JBSW5Fekptb3c?oc=5",
      "summary": "2025年度の「ラーメン店」倒産は2番目 人手不足や値上げが影響 (2026年4月8日掲載)  ライブドアニュース",
      "published": "Wed, 08 Apr 2026 07:00:00 GMT",
      "label": "ラーメン・飲食",
      "categories": [
        "restaurant"
      ]
    },
    {
      "title": "2025年の「焼肉店」倒産 46件 年間最多を更新 値上げ・高級化で客離れ加速、低価格チェーンとの競争激化 - 東京商工リサーチ",
      "link": "https://news.google.com/rss/articles/CBMiZkFVX3lxTE9XdmllSFJ6T1lKbS1sQmZrWTJXNjVTbnl6TVBuQnM1S19nZmVlS09Ra3lTVUluYTk2MzhHUjdRMjFGMjNjQ1N0U09BOTZncEVZb1NfMjJIQ0Y2V1Jyd2VDOFFRRnFIZw?oc=5",
      "summary": "2025年の「焼肉店」倒産 46件 年間最多を更新 値上げ・高級化で客離れ加速、低価格チェーンとの競争激化  東京商工リサーチ",
      "published": "Fri, 31 Oct 2025 07:00:00 GMT",
      "label": "ラーメン・飲食",
      "categories": [
        "restaurant"
      ]
    },
    {
      "title": "「町中華」の“息切れ倒産”が増加 ブームにも支えられ職人技で踏ん張ってきたが… 大手チェーンは値上げでも絶好調 - AERA DIGITAL",
      "link": "https://news.google.com/rss/articles/CBMiWkFVX3lxTE9VVk9iRDhxQV8ybVVLaTFDMUdGc2xHX0w5Y01HNEMyMUZEcXQ5SDJ4bWlhSE85Wms4NlJGRjBwNTZCWnRDVEQwaTR3LTRyeV95Rm1fOTdJOTA1UQ?oc=5",
      "summary": "「町中華」の“息切れ倒産”が増加 ブームにも支えられ職人技で踏ん張ってきたが… 大手チェーンは値上げでも絶好調  AERA DIGITAL",
      "published": "Wed, 19 Nov 2025 08:00:00 GMT",
      "label": "ラーメン・飲食",
      "categories": [
        "restaurant"
      ]
    },
    {
      "title": "「ランチ2000円」でも赤字 飲食店の利益はどこに消えるのか？ #エキスパートトピ（山路力也） - エキスパート - Yahoo!ニュース",
      "link": "https://news.google.com/rss/articles/CBMiiAFBVV95cUxPUDRHdnljYWJlS3Fva3N3dUtoVzZKTDA0UXZ6SkxqSm9Fa0Q3NlZDd0R4TU5HZFE3ZGZ5SUlNTDB6dHVMWThWRWR4OGpuNjRwZmR2XzE3RkxhanBLVFJFZU9YNk03ekpDdzRDQ0ZNTXFQZ0oxdGYtOGFHU096SjNWVW1xYm53WElv?oc=5",
      "summary": "「ランチ2000円」でも赤字 飲食店の利益はどこに消えるのか？ #エキスパートトピ（山路力也） - エキスパート  Yahoo!ニュース",
      "published": "Wed, 28 Jan 2026 08:00:00 GMT",
      "label": "ラーメン・飲食",
      "categories": [
        "restaurant"
      ]
    },
    {
      "title": "ハンバーガー店の倒産、過去最多に 値上げに踏み切れず“息切れ倒産”も (ITmedia ビジネスオンライン) - newspicks.com",
      "link": "https://news.google.com/rss/articles/CBMiTEFVX3lxTE5ORGFXa3JnQ1dHTjVJRkUzVnpqdkppVTdpdzJ4Yklub0J6SktjM3dfZFBSeEl3ZkVkdjVWdkNBcjFFUG4yVTcwQlVXNHk?oc=5",
      "summary": "ハンバーガー店の倒産、過去最多に 値上げに踏み切れず“息切れ倒産”も (ITmedia ビジネスオンライン)  newspicks.com",
      "published": "Sun, 09 Nov 2025 08:00:00 GMT",
      "label": "ラーメン・飲食",
      "categories": [
        "restaurant"
      ]
    },
    {
      "title": "ラーメンチェーン『天下一品』、首都圏で閉店ラッシュ。原因はフランチャイズ離れか？ - 飲食店ドットコム",
      "link": "https://news.google.com/rss/articles/CBMiXEFVX3lxTFBveG1nRDdQUUFxbEg0TDdYdTZfRnBJWEZOdWUwU0VtSlprdmVFUEF4UmxaS2pGSk1lMmIzaFl1QldjMWlaeG92cWZ2VXdrXzJWUS1zV3hERmtsTFlz?oc=5",
      "summary": "ラーメンチェーン『天下一品』、首都圏で閉店ラッシュ。原因はフランチャイズ離れか？  飲食店ドットコム",
      "published": "Tue, 17 Jun 2025 07:00:00 GMT",
      "label": "ラーメン・飲食",
      "categories": [
        "restaurant"
      ]
    },
    {
      "title": "日本経済新聞 印刷画面 - 日本経済新聞",
      "link": "https://news.google.com/rss/articles/CBMikAFBVV95cUxOU2VlbGtvWkttZTM1SUJMNFZBb1NFUUVxTFJCaDZGX0tLZ3hPZnZ5SEZlc3RNaVhtMjh4bV9hV0c5a24ta2hKQkJ5djRZX3dpWnhiOXZKVndTVTRBZUU3UWRDdUNxUzctalFKM3laNjNwRF9sRVNLWDdLV3ZvNUV1UDRfWHBqRnFPQ2RvMDdFZ1U?oc=5",
      "summary": "日本経済新聞 印刷画面  日本経済新聞",
      "published": "Wed, 08 Apr 2026 07:00:00 GMT",
      "label": "ラーメン・飲食",
      "categories": [
        "restaurant"
      ]
    },
    {
      "title": "ラーメン店の倒産が過去最多：コスト増も「1000円の壁」に阻まれる - nippon.com",
      "link": "https://news.google.com/rss/articles/CBMiV0FVX3lxTE9YM0RRekZpSmlOcXFWRUdkOXl1RWlmQ3cwRjY0aERaenFKZDBDdVRDNlhlY2hKRjhPRGZzVEcySGsyc3RyV2gzZnZObk1oYXBYcVN5ZDlLaw?oc=5",
      "summary": "ラーメン店の倒産が過去最多：コスト増も「1000円の壁」に阻まれる  nippon.com",
      "published": "Tue, 11 Feb 2025 08:00:00 GMT",
      "label": "ラーメン・飲食",
      "categories": [
        "restaurant"
      ]
    }
  ],
  "analysis": {
    "alert_level": "high",
    "headline": "ラーメン店倒産最多、コスト増と消費減の挟み撃ち",
    "highlights": [
      {
        "tag": "【コスト】",
        "text": "中東情勢悪化によりナフサ高騰、ビニール袋・トレーなどの包装資材仕入れ価格が30%上昇しています（記事27, 29, 30）。テイクアウトや店内提供時の資材コストが大幅に増加するリスクがあります。また、キャベツの仕入れ価格が30円アップしており（記事33）、野菜トッピングの原価増が懸念されます。円建て輸入物価は2024年7月以来の伸びで、日銀も円安による物価押し上げ効果が近年大きくなっていると報告しており（記事39, 43）、小麦、豚骨、醤油などの輸入食材の高止まり・再上昇は必至です。2026年4月にはガソリン・食品・社会保険料のさらなる値上げが予定されており（記事28）、将来的なコスト圧迫が確実です。"
      },
      {
        "tag": "【人件費】",
        "text": "2025年度の最低賃金改定により人件費高騰が確実で、飲食店の15%が経営継続が危ういと回答しています（記事45, 46）。飲食業界の平均給与は2025年度上期に上昇し、東京では月給30万円台になる見込みです（記事47）。人材確保のためには、最低賃金だけでなく「理想は1200円」程度の時給提示が必要な状況です（記事52）。人手不足対策として、ロボットや冷凍テクノロジーの導入が“切り札”として注目されており（記事48）、業務効率化による人件費抑制も検討すべきです。"
      },
      {
        "tag": "【客数・消費】",
        "text": "「子ども・子育て支援金」の給与天引きが今月から始まり（記事22）、消費者の実質的な手取り減少による外食支出抑制リスクがあります。特に「食料品の消費税ゼロ」案が導入された場合、外食が対象外となるため、スーパーでの食材購入が割安となり、飲食店からの客離れを招く可能性が極めて高く、日本フードサービス協会も強く懸念を表明しています（記事31, 32, 53, 54, 56）。外食の2025年全店売上高は7.3%増ですが、これは単価上昇によるもので客数は頭打ち感が強く（記事60）、低価格路線のサイゼリヤは客数を増やしているものの、消費者の財布の紐は固い状況です（記事57）。この夏も全国的に平年より気温が高い見込みで（記事24）、ラーメン離れの季節リスクがあります。梅雨期の多雨も客足減少につながる可能性があります。"
      },
      {
        "tag": "【競合・業界】",
        "text": "2025年度のラーメン店倒産は57件と過去2番目の多さ（記事63）、または過去最多（記事72）であり、物価高や人手不足、値上げが主要因です（記事65）。特に「1000円の壁」に阻まれ、コスト増を価格転嫁できない状況が倒産を加速させています（記事72）。飲食店全体で「値上げすれば客離れ、しなければ倒産」というジレンマに直面し、価格転嫁率が32.3%と低い現実があります（記事64）。町中華の倒産も増加しており、大手チェーンは値上げでも好調な一方で、個人店や小規模チェーンの二極化が進行しています（記事67）。さらに、大手ラーメンチェーン「天下一品」が首都圏で閉店ラッシュ（記事70）という状況は、ラーメン業界全体の収益性悪化と厳しさを象徴しています。"
      },
      {
        "tag": "【世界情勢→経営】",
        "text": "中東情勢悪化（記事27）や中ロ首脳会談（記事3）など地政学リスクの継続は、原油価格高騰を招き、燃料費、電気・ガス代、輸送費、包装資材（ナフサ由来）のコスト上昇に直接影響します。高性能AIモデル「クロード・ミュトス」によるサイバー攻撃リスク（記事7, 14）は、店舗のPOSシステムや顧客情報システムへのセキュリティ対策の重要性を高め、情報漏洩によるブランドイメージ毀損リスクを認識すべきです。コンビニ各社がプラスチック削減を進めている（記事17）のは、プラスチック原材料高騰が背景にあり、ラーメン店もテイクアウト容器などの見直しや、代替素材への移行コストを検討する必要があるでしょう。"
      }
    ],
    "actions": [
      {
        "what": "今週中に夏季限定冷やし系メニューのプロモーション計画を策定し、梅雨対策としてデリバリー強化策（雨の日割引、特典など）を検討する。",
        "why": "気象庁の3か月予報で「この夏も気温が高い見込み、梅雨期は多雨のおそれ」（記事24）があり、ラーメン需要の季節的変動と客足減少リスクに対応するため。",
        "when": "今週中"
      },
      {
        "what": "今月中にも、テイクアウト容器やレジ袋などのプラスチック資材の仕入れ先を複数検討し、一部を紙製やバイオマス素材へ切り替えるための見積もりを取得する。",
        "why": "中東情勢悪化でナフサ高騰により、ビニール袋・トレーなど包装資材の仕入れ価格が30%上昇している（記事27, 29, 30）ため、コスト増を吸収しつつ代替策を講じる必要があるから。",
        "when": "今月中"
      },
      {
        "what": "今週中に、既存のアルバイト従業員の時給を近隣競合店の募集時給（「理想は1200円」などの情報も考慮し）と2025年度の最低賃金引き上げ見込みを考慮して再評価し、採用活動においては地域の最低賃金プラスαの競争力ある時給を提示できるよう経営計画を見直す。",
        "why": "2025年度の最低賃金改定で「飲食店の15%が経営継続が危うい」と回答（記事46）し、飲食店での「人手不足倒産」が懸念されており、「最低賃金だけではアルバイトは来ない」（記事52）状況だから。",
        "when": "今週中"
      }
    ],
    "cost_items": [
      {
        "name": "包装資材（ビニール袋、トレー）",
        "direction": "上昇",
        "detail": "仕入れ価格30%↑（記事27, 29, 30）"
      },
      {
        "name": "キャベツ",
        "direction": "上昇",
        "detail": "仕入れ価格30円アップ（記事33）"
      },
      {
        "name": "輸入食材（小麦、豚骨、醤油など）",
        "direction": "上昇",
        "detail": "円建て輸入物価が2024年7月以来の伸び、円安ショック後の物価押し上げが大きい（記事39, 43）"
      },
      {
        "name": "燃料費（電気、ガス、輸送費）",
        "direction": "上昇",
        "detail": "中東情勢悪化、地政学リスクによる原油価格高騰リスク（記事3, 27）"
      },
      {
        "name": "人件費",
        "direction": "上昇",
        "detail": "2025年度最低賃金改定、飲食業界平均給与上昇、理想時給1200円（記事45, 47, 52）"
      },
      {
        "name": "消耗品",
        "direction": "上昇",
        "detail": "100円ショップの仕入れ値次々上昇から推測（記事35）"
      }
    ],
    "relevant_indices": [
      2,
      3,
      4,
      7,
      14,
      17,
      20,
      22,
      24,
      27,
      28,
      29,
      30,
      31,
      32,
      33,
      34,
      35,
      36,
      37,
      38,
      39,
      40,
      41,
      42,
      43,
      44,
      45,
      46,
      47,
      48,
      49,
      50,
      51,
      52,
      53,
      54,
      55,
      56,
      57,
      58,
      59,
      60,
      61,
      62,
      63,
      64,
      65,
      66,
      67,
      68,
      69,
      70,
      72
    ]
  }
}