{
  "date": "2026-05-31",
  "generated_at": "2026-05-31T22:45:22.502221",
  "articles": [
    {
      "title": "【台風6号】沖縄・奄美に接近 西・東日本でも大雨・暴風おそれ",
      "link": "https://news.web.nhk/newsweb/na/na-k10015136781000",
      "summary": "台風6号は、これからあすにかけて沖縄・奄美にかなり接近する見込みで、猛烈な風が吹き、雨も非常に激しく降るおそれがあります。気象庁は、暴風や高波、土砂災害、低い土地の浸水などに厳重に警戒するよう呼びかけ…",
      "published": "Mon, 01 Jun 2026 07:06:33 +0900",
      "label": "NHKトップ",
      "categories": [
        "general"
      ]
    },
    {
      "title": "【熱中症対策を】東日本と北日本中心に気温上昇 猛暑日予想も",
      "link": "https://news.web.nhk/newsweb/na/na-k10015136801000",
      "summary": "東日本と北日本を中心にきょうも晴れて気温が上がり35度以上の猛暑日となるところもある見込みです。こまめに水分補給をするなど熱中症への対策を心がけてください。",
      "published": "Mon, 01 Jun 2026 05:54:19 +0900",
      "label": "NHKトップ",
      "categories": [
        "general"
      ]
    },
    {
      "title": "診療報酬改定 医療機関の収入と患者の窓口負担ともに増加へ",
      "link": "https://news.web.nhk/newsweb/na/na-k10015136631000",
      "summary": "医療機関に支払われる診療報酬が6月1日から改定されます。物価高や医療従事者の賃上げへの対応として、外来や入院の基本料が引き上げられるなど医療機関の収入が増える一方、患者の窓口負担も増えることになります…",
      "published": "Mon, 01 Jun 2026 05:19:46 +0900",
      "label": "NHKトップ",
      "categories": [
        "general"
      ]
    },
    {
      "title": "“イラン側も覚書に修正追加” 米大統領の修正要求報道に",
      "link": "https://news.web.nhk/newsweb/na/na-k10015136771000",
      "summary": "アメリカとイランの協議の担当者が暫定的に一致したとされる覚書にトランプ大統領が修正を求めたと報じられるなか、イランの革命防衛隊とつながりのあるタスニム通信は31日、イラン側も修正を加えるとする情報筋の…",
      "published": "Mon, 01 Jun 2026 06:29:42 +0900",
      "label": "NHKトップ",
      "categories": [
        "general"
      ]
    },
    {
      "title": "【台風影響】沖縄発着便中心にきょう約400便が欠航",
      "link": "https://news.web.nhk/newsweb/na/na-k10015136811000",
      "summary": "国内の主な航空会社によりますと、台風の影響で、沖縄を発着する便を中心にきょうはおよそ400便が欠航となっています。",
      "published": "Mon, 01 Jun 2026 06:34:11 +0900",
      "label": "NHKトップ",
      "categories": [
        "general"
      ]
    },
    {
      "title": "安定的な皇位継承 衆参両院の議長・副議長 今週再会談へ",
      "link": "https://news.web.nhk/newsweb/na/na-k10015136701000",
      "summary": "安定的な皇位継承をめぐり、衆参両院の議長・副議長は、とりまとめ案の作成に向けて、今週、改めて会談することにしています。各党・各会派の意見も踏まえ、できるだけ幅広い賛同を得たいとして文言の調整などを急ぐ…",
      "published": "Mon, 01 Jun 2026 05:22:21 +0900",
      "label": "NHKトップ",
      "categories": [
        "general"
      ]
    },
    {
      "title": "名古屋 住宅で火事 2人が意識ない状態で搬送",
      "link": "https://news.web.nhk/newsweb/na/na-k10015136821000",
      "summary": "1日未明、名古屋市の住宅で火事があり、2人が意識がない状態で病院に搬送されました。",
      "published": "Mon, 01 Jun 2026 06:38:35 +0900",
      "label": "NHKトップ",
      "categories": [
        "general"
      ]
    },
    {
      "title": "将棋 叡王戦 伊藤匠二冠 タイトル防衛で3連覇",
      "link": "https://news.web.nhk/newsweb/na/na-k10015136281000",
      "summary": "将棋の八大タイトルの1つ、「叡王戦」五番勝負の最終局が千葉県で行われ、伊藤匠 二冠が挑戦者の斎藤慎太郎 八段に勝ってタイトルを防衛し、3連覇を果たしました。",
      "published": "Sun, 31 May 2026 22:31:39 +0900",
      "label": "NHK経済",
      "categories": [
        "economy"
      ]
    },
    {
      "title": "米建国250年記念コンサート アーティストの出演辞退相次ぐ",
      "link": "https://news.web.nhk/newsweb/na/na-k10015136391000",
      "summary": "アメリカの建国250年を祝う行事の一環として予定されているコンサートで、アーティストの出演辞退が相次いでいて、トランプ大統領は、アーティストを批判するとともに、自身が演説を行う場とする考えを示しました…",
      "published": "Sun, 31 May 2026 13:30:16 +0900",
      "label": "NHK経済",
      "categories": [
        "economy"
      ]
    },
    {
      "title": "エリザベート王妃国際音楽コンクール チェロで北村陽さん入賞",
      "link": "https://news.web.nhk/newsweb/na/na-k10015136251000",
      "summary": "ベルギーで開かれた世界3大音楽コンクールの1つ「エリザベート王妃国際音楽コンクール」のチェロ部門で、兵庫県出身の北村陽さんが5位に選ばれました。",
      "published": "Sun, 31 May 2026 10:22:19 +0900",
      "label": "NHK経済",
      "categories": [
        "economy"
      ]
    },
    {
      "title": "北極海の氷の厚さ推定する新手法開発 人工衛星のデータ活用",
      "link": "https://news.web.nhk/newsweb/na/na-k10015136111000",
      "summary": "地球温暖化が進むなか、北極海の氷の減少について詳しく調べようと、高知大学などの研究チームは人工衛星の観測データをもとに氷の厚さを推定する新たな手法を開発しました。気候変動の予測精度の向上につながると期…",
      "published": "Sun, 31 May 2026 06:02:30 +0900",
      "label": "NHK経済",
      "categories": [
        "economy"
      ]
    },
    {
      "title": "日本のポップカルチャー紹介 ドイツで最大規模のイベント開始",
      "link": "https://news.web.nhk/newsweb/na/na-k10015135791000",
      "summary": "日本のアニメやゲームなどポップカルチャーへの関心が高まるドイツで、29日、国内最大規模のイベントが始まりました。",
      "published": "Sat, 30 May 2026 14:03:10 +0900",
      "label": "NHK経済",
      "categories": [
        "economy"
      ]
    },
    {
      "title": "【解説動画】iPS細胞の治療 実用化 失われた体の機能再生",
      "link": "https://news.web.nhk/newsweb/na/na-k10015135771000",
      "summary": "これまでの常識を覆す革新的な医療となるか、iPS細胞を使う治療がいよいよ始まります。iPS細胞から体のさまざまな細胞を作り、患者に移植することで病気やけがで失われた体の機能を再生させる“夢の医療”にも…",
      "published": "Sat, 30 May 2026 08:53:19 +0900",
      "label": "NHK経済",
      "categories": [
        "economy"
      ]
    },
    {
      "title": "高市首相 次世代エネルギー普及に取り組む考え 小池知事らに",
      "link": "https://news.web.nhk/newsweb/na/na-k10015135361000",
      "summary": "高市総理大臣は、水素社会の実現を目指す自治体のトップと面会し、次世代のエネルギーとして期待される水素やアンモニアの普及に取り組む考えを示しました。",
      "published": "Fri, 29 May 2026 19:50:29 +0900",
      "label": "NHK経済",
      "categories": [
        "economy"
      ]
    },
    {
      "title": "事件の偽情報でアプリ登録誘導 「詳細はここから」に注意",
      "link": "https://news.web.nhk/newsweb/na/na-k10015135351000",
      "summary": "栃木県上三川町で起きた強盗殺人事件について、容疑者に関する偽の情報とともに「限定公開」とか「詳細はここから」などとして、リンクに誘導する投稿がSNSで相次いでいます。クリックすると、動画視聴アプリへの…",
      "published": "Fri, 29 May 2026 19:40:23 +0900",
      "label": "NHK経済",
      "categories": [
        "economy"
      ]
    },
    {
      "title": "米アンソロピック 「ミュトス」級AI 数週間以内に全顧客提供へ",
      "link": "https://news.web.nhk/newsweb/na/na-k10015134691000",
      "summary": "アメリカのAI新興企業アンソロピックは28日、サイバー攻撃に悪用されるおそれがあるとして一般への公開を見送っていた高性能なAIモデル「クロード・ミュトス」と同じ水準のモデルを数週間以内にすべての顧客に…",
      "published": "Fri, 29 May 2026 10:41:56 +0900",
      "label": "NHK経済",
      "categories": [
        "economy"
      ]
    },
    {
      "title": "エアコン事故に注意 本格的な夏前に周辺の点検と試運転を",
      "link": "https://news.web.nhk/newsweb/na/na-k10015134491000",
      "summary": "暑さが本格化する夏場に、エアコンが関係する事故が増えることから、NITE＝製品評価技術基盤機構は、早めに周辺を点検して、エアコンの試運転をするように呼びかけています。",
      "published": "Thu, 28 May 2026 23:50:33 +0900",
      "label": "NHK経済",
      "categories": [
        "economy"
      ]
    },
    {
      "title": "将棋 羽生九段敗れタイトル通算100期挑戦ならず",
      "link": "https://news.web.nhk/newsweb/na/na-k10015134391000",
      "summary": "28日に東京の将棋会館で行われた八大タイトルのひとつ「王位戦」の挑戦者決定戦で羽生善治九段が伊藤匠二冠に敗れ、通算タイトル100期を目指すタイトル挑戦はなりませんでした。",
      "published": "Thu, 28 May 2026 21:17:58 +0900",
      "label": "NHK経済",
      "categories": [
        "economy"
      ]
    },
    {
      "title": "大飯原発設置許可取り消し訴訟 原告側の訴え退ける 大阪高裁",
      "link": "https://news.web.nhk/newsweb/na/na-k10015133631000",
      "summary": "福井県にある関西電力大飯原子力発電所に対して国が行った設置許可の是非が争われた裁判で2審の大阪高等裁判所は、設置許可を取り消した1審とは逆に、市民グループの訴えを退ける判決を言い渡しました。",
      "published": "Thu, 28 May 2026 19:07:45 +0900",
      "label": "NHK経済",
      "categories": [
        "economy"
      ]
    },
    {
      "title": "【動画】Pickup NEWS（6月1日）",
      "link": "https://news.web.nhk/newsweb/na/na-k10015136491000",
      "summary": "これまでに入っているニュースを、まとめて1分の動画でお伝えします。（データ放送では動画をご覧いただけません）",
      "published": "Mon, 01 Jun 2026 07:26:47 +0900",
      "label": "NHK社会",
      "categories": [
        "general"
      ]
    },
    {
      "title": "【地震速報】新潟県で震度3 津波の心配なし",
      "link": "https://news.web.nhk/newsweb/na/na-k10015136321000",
      "summary": "きょう午前5時54分ごろ新潟県で震度3の揺れを観測する地震がありました。この地震による津波の心配はありません。",
      "published": "Mon, 01 Jun 2026 06:17:32 +0900",
      "label": "NHK社会",
      "categories": [
        "general"
      ]
    },
    {
      "title": "国民的アイドルグループ「嵐」２６年半の活動終える",
      "link": "https://news.web.nhk/newsweb/na/na-k10015136741000",
      "summary": "国民的な人気アイドルグループ「嵐」が31日東京ドームで行われたコンサートをもってデビューから26年半にわたる活動を終えました。",
      "published": "Mon, 01 Jun 2026 05:36:44 +0900",
      "label": "NHK社会",
      "categories": [
        "general"
      ]
    },
    {
      "title": "沖縄 南城市 市内全域に避難指示",
      "link": "https://news.web.nhk/newsweb/na/na-k10015136791000",
      "summary": "沖縄県南城市は暴風警報の発表を受けて、1日午前4時25分、市内全域に避難指示を出しました。危険な場所から全員避難するよう呼びかけています。",
      "published": "Mon, 01 Jun 2026 05:02:21 +0900",
      "label": "NHK社会",
      "categories": [
        "general"
      ]
    },
    {
      "title": "【台風6号】沖縄・奄美に1日から接近 暴風や大雨など厳重警戒",
      "link": "https://news.web.nhk/newsweb/na/na-k10015136211000",
      "summary": "台風6号は、6月1日には強い勢力で沖縄・奄美に接近し、その後、3日にかけて西日本と東日本にも暴風域を伴って近づくおそれがあります。沖縄・奄美では1日から猛烈な風が吹き、大雨になるおそれがあるほか、九州…",
      "published": "Sun, 31 May 2026 22:55:54 +0900",
      "label": "NHK社会",
      "categories": [
        "general"
      ]
    },
    {
      "title": "【台風影響】沖縄発着便など6月2日にかけて計400便以上が欠航",
      "link": "https://news.web.nhk/newsweb/na/na-k10015136311000",
      "summary": "国内の主な航空会社によりますと、台風の影響で、沖縄を発着する便を中心に31日から6月2日にかけてあわせて400便以上が欠航となっています（午後8時現在）。",
      "published": "Sun, 31 May 2026 21:23:26 +0900",
      "label": "NHK社会",
      "categories": [
        "general"
      ]
    },
    {
      "title": "【動画】Pickup NEWS（5月31日）",
      "link": "https://news.web.nhk/newsweb/na/na-k10015136091000",
      "summary": "これまでに入っているニュースを、まとめて1分の動画でお伝えします。（データ放送では動画をご覧いただけません）",
      "published": "Sun, 31 May 2026 19:59:28 +0900",
      "label": "NHK社会",
      "categories": [
        "general"
      ]
    },
    {
      "title": "沖縄 宮古島 市内全域に高齢者等避難情報",
      "link": "https://news.web.nhk/newsweb/na/na-k10015136611000",
      "summary": "沖縄県宮古島市は台風6号の接近に伴い31日午後5時、市内全域に高齢者等避難の情報を出しました。高齢者や体の不自由な人などに避難を始めるよう呼びかけています。",
      "published": "Sun, 31 May 2026 19:51:31 +0900",
      "label": "NHK社会",
      "categories": [
        "general"
      ]
    },
    {
      "title": "アジア安全保障会議 閉幕 “中堅国中心に連携強化必要”意見も",
      "link": "https://news.web.nhk/newsweb/na/na-k10015136581000",
      "summary": "各国の防衛担当の閣僚らが集まる「アジア安全保障会議」が、31日、閉幕しました。会議では、アメリカと中国が互いにけん制しつつも安定した関係を構築させる姿勢を示した一方、東南アジアの国々からは、大国に依存…",
      "published": "Sun, 31 May 2026 19:27:35 +0900",
      "label": "NHK社会",
      "categories": [
        "general"
      ]
    },
    {
      "title": "1日は東日本 北日本で高温続く 猛暑日のところも 熱中症対策を",
      "link": "https://news.web.nhk/newsweb/na/na-k10015136601000",
      "summary": "31日は高気圧に覆われ広い範囲で気温が上がり、各地で30度以上の真夏日となりました。6月1日は台風や湿った空気の影響で西日本を中心に雨や曇りとなる一方、東日本と北日本では気温が高い状態が続く見込みで、…",
      "published": "Sun, 31 May 2026 19:26:21 +0900",
      "label": "NHK社会",
      "categories": [
        "general"
      ]
    },
    {
      "title": "中東情勢悪化でナフサ高騰 ビニール袋・トレー“包装資材”の仕入れ30％↑にスーパー悲鳴「今度は何が値上がりするのか」 - Yahoo!ニュース",
      "link": "https://news.google.com/rss/articles/CBMif0FVX3lxTE1nZUVyYTdjcmR5bG01Z0xDUFN3azg5Sk9CQi1hb1lON1BfcGRpUFRlOHk4ZnY2TnIxMm5rVXhZSTNFUy1uV2ZwYm5VeUYwbGl1bWM4RnV0cGNGWnZjNGtnRExPYi0zWnh4NDVUUk1TNFlfX1hXME1ERTBQeEFpbUk?oc=5",
      "summary": "中東情勢悪化でナフサ高騰 ビニール袋・トレー“包装資材”の仕入れ30％↑にスーパー悲鳴「今度は何が値上がりするのか」  Yahoo!ニュース",
      "published": "Wed, 13 May 2026 07:00:00 GMT",
      "label": "食材値上がり",
      "categories": [
        "cost"
      ]
    },
    {
      "title": "県民のソウルフード「焼き鳥」にも影響 鶏肉の高騰続く 2003年の調査開始以来最高値に 鳥インフルと中東情勢が影響か - 日テレNEWS NNN",
      "link": "https://news.google.com/rss/articles/CBMif0FVX3lxTE16N1p6U1Mxckx1QmdQRGx5YkNvZVRqdjBINDhJUXVHNVVrb3U5VlZJR3lwbWpiM2FlNHRZQnExTkZzckVCYlBNRVZJTVBqX0VEWEIzdGZmMFlJVnBkSkh1aXMxUnhGVlRjbnMxUms2YkhfYkpjdzFMcXlUWXN4MlU?oc=5",
      "summary": "県民のソウルフード「焼き鳥」にも影響 鶏肉の高騰続く 2003年の調査開始以来最高値に 鳥インフルと中東情勢が影響か  日テレNEWS NNN",
      "published": "Thu, 21 May 2026 10:15:01 GMT",
      "label": "食材値上がり",
      "categories": [
        "cost"
      ]
    },
    {
      "title": "【税理士監修・2026年4月値上げ一覧】経営への影響は？ガソリン・食品・固定電話・社会保険料まで経営者が今すぐ打つべき対策 - sogyotecho.jp",
      "link": "https://news.google.com/rss/articles/CBMiS0FVX3lxTE1kcmNJUEZOck5qdmhvSFZHaElUaGo2Vi1TMTVjcFBheklWaG9Ic0p3Ylc5R21GdHFpVzR1T2FITlg1N3lyTU1XQXhRYw?oc=5",
      "summary": "【税理士監修・2026年4月値上げ一覧】経営への影響は？ガソリン・食品・固定電話・社会保険料まで経営者が今すぐ打つべき対策  sogyotecho.jp",
      "published": "Tue, 14 Apr 2026 07:00:00 GMT",
      "label": "食材値上がり",
      "categories": [
        "cost"
      ]
    },
    {
      "title": "“包装資材”値上げでスーパーから悲鳴 ビニール袋・トレーの仕入れ30％↑に「どんどん売りづらくなっている」 - 新潟ニュース NST",
      "link": "https://news.google.com/rss/articles/CBMiX0FVX3lxTE9vTGdnTFZUWEdmSVRLUTBZMEJ3NmlFWTZabzRzU050enZET3AtSmZBOTczY0d3Um1kWjVCWjJMWGZ1ZXg2RmE0RzRvM2xkODZEQlZkMlZfU3Q5UE55TVNV?oc=5",
      "summary": "“包装資材”値上げでスーパーから悲鳴 ビニール袋・トレーの仕入れ30％↑に「どんどん売りづらくなっている」  新潟ニュース NST",
      "published": "Fri, 01 May 2026 07:00:00 GMT",
      "label": "食材値上がり",
      "categories": [
        "cost"
      ]
    },
    {
      "title": "【4月以降に値上げする食品・生活必需品リスト】原油高騰がプラスチック製品を直撃、刺身や肉のトレー、小分け包装されているものに影響大 「買いだめで損をする」落とし穴に注意 - マネーポストWEB",
      "link": "https://news.google.com/rss/articles/CBMiR0FVX3lxTE10bkcyYlNiMEhzbVI4OXVRamloX0prcm9TZEFobFkyWHQydnpRTC1DWXBLUzYwV0pBRlcyVnV5M1lRUjl6V3FR?oc=5",
      "summary": "【4月以降に値上げする食品・生活必需品リスト】原油高騰がプラスチック製品を直撃、刺身や肉のトレー、小分け包装されているものに影響大 「買いだめで損をする」落とし穴に注意  マネーポストWEB",
      "published": "Wed, 25 Mar 2026 07:00:00 GMT",
      "label": "食材値上がり",
      "categories": [
        "cost"
      ]
    },
    {
      "title": "【湖東京至税理士に聞く】総選挙 消費税の食料品ゼロ％は大問題 - 全国商工団体連合会",
      "link": "https://news.google.com/rss/articles/CBMiXkFVX3lxTE0xUjZYOF9NVkI5ZWNqM1AyYnNqb3BPVndoV1gwYTMxRVhVRS0tWWkzb2ZZZmh3RVgwaG8ybk1SNWJIbnczcGxGd0o0QURWLWRuWlhjb2Y1MW5TWThQSFE?oc=5",
      "summary": "【湖東京至税理士に聞く】総選挙 消費税の食料品ゼロ％は大問題  全国商工団体連合会",
      "published": "Sun, 08 Feb 2026 08:00:00 GMT",
      "label": "食材値上がり",
      "categories": [
        "cost"
      ]
    },
    {
      "title": "食料品消費税ゼロで飲食店経営はどう変わる？「仕入税額控除」から読み解く致命的なリスク | 飲食店ドットコム ジャーナル - 飲食店ドットコム",
      "link": "https://news.google.com/rss/articles/CBMiXEFVX3lxTE90XzVDU29VTHE5WlhfMVI1cl90QjhCNWpxZDdaN1U3dmE1WktmRzk1aEJobnpSWVkxZWZ3YWJtQTdKNjBwV0l5WnJ3UU1sN3Z6TGZoeXpTUkVNUzRF?oc=5",
      "summary": "食料品消費税ゼロで飲食店経営はどう変わる？「仕入税額控除」から読み解く致命的なリスク | 飲食店ドットコム ジャーナル  飲食店ドットコム",
      "published": "Thu, 29 Jan 2026 08:00:00 GMT",
      "label": "食材値上がり",
      "categories": [
        "cost"
      ]
    },
    {
      "title": "「食料品消費税ゼロ」で飲食店が倒産危機？問題は\"値下げしない\"か\"内容量を減らす\"こと - 寺田税理士･社会保険労務士事務所",
      "link": "https://news.google.com/rss/articles/CBMiY0FVX3lxTE9xWldNWV85U2h0ZDJPdURZeEV5LXhhbDUxSC14U2phaGxxMHBpMzhlSGw4a21VdFd1bjlkZndCS0gyQ2U4MGZtX0NucEpuQzNpSGo0dUx5NXJTcG5NV29qWHdGOA?oc=5",
      "summary": "「食料品消費税ゼロ」で飲食店が倒産危機？問題は\"値下げしない\"か\"内容量を減らす\"こと  寺田税理士･社会保険労務士事務所",
      "published": "Sat, 24 Jan 2026 08:00:00 GMT",
      "label": "食材値上がり",
      "categories": [
        "cost"
      ]
    },
    {
      "title": "キャベツの仕入れ価格30円アップ 販売価格194円 生育の端境期で価格上昇 レタス価格は安定 - 愛知のニュース",
      "link": "https://news.google.com/rss/articles/CBMiWkFVX3lxTE5RcFBiN1d2U0JoeUdzeFF1aFliZ1JlUWczeExKTi1TNkpMdmpMTFB0TERCbjVIbFhVYWlfVU9IX1pFZlloTlEyZjZSN200ckdkVGV0ZzBITnVNdw?oc=5",
      "summary": "キャベツの仕入れ価格30円アップ 販売価格194円 生育の端境期で価格上昇 レタス価格は安定  愛知のニュース",
      "published": "Wed, 08 Apr 2026 07:00:00 GMT",
      "label": "食材値上がり",
      "categories": [
        "cost"
      ]
    },
    {
      "title": "中東情勢悪化でナフサ高騰　ビニール袋・トレー“包装資材”の仕入れ30％↑にスーパー悲鳴「今度は何が値上がりするのか」 | チバテレ＋プラス - 千葉テレビ放送",
      "link": "https://news.google.com/rss/articles/CBMiX0FVX3lxTE5QTlVVMXdWd09YTHd0UHA2Zk5yZkUzVThJSTFMNEdRdS1jSHBsTDZQYVk5U0dBT0psQzlxTXowWU4xVE1yRGw2S1IybjBDUkJJS3dWRUtjWFpFQWxtck9R0gFkQVVfeXFMT09wQnROUjBGYlMyUU1WbHQyaXNjWE9XOTJRSkdyZlJsdGZNcGdCVVVIU084dVpJcHBCS0xNYWE1LU9kRnFkYU5UWTN1ZkQ2cl9uMjluMWpnUWd0Y1N6NkMwbG5oeQ?oc=5",
      "summary": "中東情勢悪化でナフサ高騰　ビニール袋・トレー“包装資材”の仕入れ30％↑にスーパー悲鳴「今度は何が値上がりするのか」 | チバテレ＋プラス  千葉テレビ放送",
      "published": "Wed, 13 May 2026 07:00:00 GMT",
      "label": "食材値上がり",
      "categories": [
        "cost"
      ]
    },
    {
      "title": "円安の抑制で日銀が為替介入 - komei.or.jp",
      "link": "https://news.google.com/rss/articles/CBMikAJBVV95cUxQajZ5X2libV80d3BiQ3VjaGFEUlFPRE9XRnBjbGdLMEpROFM1aGs1M2Y4U1hHRlhOQ2hLb2MxczVSaGx4MHZ5V294Q2FwSXc5NVpNekNJVmIydHU1dVBURU9ITjVoSzYxWC1YVnZTekFoOUZOd09sWmsxejgwNGNoSHlCU3Q2ZTZXWjh4b3U5TjZXTGpaSGR6TE8tNkl4RktOUGtBcXM4U2diS0RyZ0hUTFNxbl8zWjU5MjZFMFJuYkhkSlFrZmpSRXBOWkVkR3N5OWJwb01RdU9CMU5aM1drcWhFb1l6V19BMzY4Zzc2NWN1bUVrR3c4dkljRTl0bkN3UkpwN1lPSUFnV3EyeFl0cg?oc=5",
      "summary": "円安の抑制で日銀が為替介入  komei.or.jp",
      "published": "Sat, 16 May 2026 21:07:36 GMT",
      "label": "為替・輸入コスト",
      "categories": [
        "cost",
        "economy"
      ]
    },
    {
      "title": "再び忍び寄る円安インフレの足音、円建ての輸入物価は2024年7月以来の伸びに、インフレ圧力は国内物価に波及必至 【唐鎌大輔の為替から見る日本】4月会合では利上げ見送りの公算だが、6月、7月会合に向けた地ならしは進むか(1/3) - JBpress",
      "link": "https://news.google.com/rss/articles/CBMiVkFVX3lxTE9XY0VyZ3l1OERXTWN1bmg2b2xzUzhiTlJJN3lfT1ZkbjM5aU5aUE5aTVNnZ3VtUUc2ejhjdU9qZDQ0bUp4cTkwZlFqOVZxUUFrYXk5VVhB?oc=5",
      "summary": "再び忍び寄る円安インフレの足音、円建ての輸入物価は2024年7月以来の伸びに、インフレ圧力は国内物価に波及必至 【唐鎌大輔の為替から見る日本】4月会合では利上げ見送りの公算だが、6月、7月会合に向けた地ならしは進むか(1/3)  JBpress",
      "published": "Sat, 25 Apr 2026 07:00:00 GMT",
      "label": "為替・輸入コスト",
      "categories": [
        "cost",
        "economy"
      ]
    },
    {
      "title": "【社説】政府の為替介入円安構造に改善のメスを - 47NEWS",
      "link": "https://news.google.com/rss/articles/CBMiS0FVX3lxTE1xXy1OZndjMEpFQl9lWDlVTVFkNjJKZW1rNXZtVUJ5bmdEdWNaU2NuV2RDNk9GOEFCUWRYSDVTRGJXMlVSYWRPVWw1WQ?oc=5",
      "summary": "【社説】政府の為替介入円安構造に改善のメスを  47NEWS",
      "published": "Thu, 14 May 2026 07:00:00 GMT",
      "label": "為替・輸入コスト",
      "categories": [
        "cost",
        "economy"
      ]
    },
    {
      "title": "「悪い円安」は再び訪れるのか - 日本経済新聞",
      "link": "https://news.google.com/rss/articles/CBMifkFVX3lxTE1SaTlIZkY0c0VGNHU3bHFnYThLMThaZzAzRHR4LTBYcEIwdEN4V3I4bG1vdklqdlRWMlVaWlpKaC1SWFppaXotYVNiSy1GNVIwU0FhUURLQlZFYTBQMWg3dkZHWTQxYkZfNTQ2OGVDSU12ODVtV0s1d0lyMkgtZw?oc=5",
      "summary": "「悪い円安」は再び訪れるのか  日本経済新聞",
      "published": "Thu, 06 Nov 2025 08:00:00 GMT",
      "label": "為替・輸入コスト",
      "categories": [
        "cost",
        "economy"
      ]
    },
    {
      "title": "【社説】政府の為替介入 円安構造に改善のメスを - 西日本新聞me",
      "link": "https://news.google.com/rss/articles/CBMiVkFVX3lxTE1iSFBYYXRkMFJsa0lGN1UwY2RNU3A4ekVtbUVIczhEckVoMDE3eTBWY0VBTDFVRUZnS1ZKSWdkbkVLOHhYOUsxZTZhY1JlU09vZWRJb2Fn?oc=5",
      "summary": "【社説】政府の為替介入 円安構造に改善のメスを  西日本新聞me",
      "published": "Thu, 14 May 2026 07:00:00 GMT",
      "label": "為替・輸入コスト",
      "categories": [
        "cost",
        "economy"
      ]
    },
    {
      "title": "(クローズアップNOW)円安の抑制で日銀が為替介入 4、5月で10兆円規模か 円大幅高、一時150円台半ば 2026.5.17付 - 公明新聞電子版プラス",
      "link": "https://news.google.com/rss/articles/CBMibkFVX3lxTFBSeHM5cEhEY1cyWVlxMFRscEtZaWt6T1AxZ2p4VlBhZktUSDJTaEJxSHJXVUxDTjA0M2tQNkR6MUExUWFqYTlNWnRMeVFackRwTHZNdG9QYnJER1Y3TlVhenFfQWFyS2dpVlczdXZn?oc=5",
      "summary": "(クローズアップNOW)円安の抑制で日銀が為替介入 4、5月で10兆円規模か 円大幅高、一時150円台半ば 2026.5.17付  公明新聞電子版プラス",
      "published": "Sat, 16 May 2026 20:01:17 GMT",
      "label": "為替・輸入コスト",
      "categories": [
        "cost",
        "economy"
      ]
    },
    {
      "title": "円安ショック後の物価押し上げ、近年は大きくなっている＝日銀展望リポート - Reuters",
      "link": "https://news.google.com/rss/articles/CBMieEFVX3lxTE03eVhhWWVabGVIYmliTzloQ0I5YXNoNnRieGt2MVhleWM2UF9ZZ3dSXzJRLWtVbEZPclJDVFpDSGZyYlRLY29KVnkyeG5tZkwyeVJtVXRtSG8zRFM5YlIyQmZjeVVjOHZxQVNZZ3ZTNTU3SUg0dVJzUA?oc=5",
      "summary": "円安ショック後の物価押し上げ、近年は大きくなっている＝日銀展望リポート  Reuters",
      "published": "Sun, 25 Jan 2026 08:00:00 GMT",
      "label": "為替・輸入コスト",
      "categories": [
        "cost",
        "economy"
      ]
    },
    {
      "title": "高市政権下で強まる円安基調、為替介入に神経尖らせる市場-QuickTake - Bloomberg.com",
      "link": "https://news.google.com/rss/articles/CBMid0FVX3lxTE5nUDB1c2VOcWIxTW95eGZONWlORUJiV1Bhb21SYkxxVUxDZnZVLUxzRVFyMmJsQWU0Y1Z6b194M0RTa3l1NDRCUUw1WWRmQ2w3b1J3VzJPWldQbWMwNDlJTkFlYW40ZldnVWZRcDRsbDZ3UUY0emc0?oc=5",
      "summary": "高市政権下で強まる円安基調、為替介入に神経尖らせる市場-QuickTake  Bloomberg.com",
      "published": "Tue, 11 Nov 2025 08:00:00 GMT",
      "label": "為替・輸入コスト",
      "categories": [
        "cost",
        "economy"
      ]
    },
    {
      "title": "2025年度の最低賃金改定について独自調査。飲食店での人件費高騰への具体的な対策は？ - 飲食店ドットコム",
      "link": "https://news.google.com/rss/articles/CBMiXEFVX3lxTE12VmtwU2NFTFFFbzdDRUVrSXptVmgzTDlESjc0djhhT2dxckgyYWJZQ3JzSE5HUzhUMTdlMGszd3BvNW50cFA3YXdTMXpkbEttVmY3bXVtQl91TmVH?oc=5",
      "summary": "2025年度の最低賃金改定について独自調査。飲食店での人件費高騰への具体的な対策は？  飲食店ドットコム",
      "published": "Wed, 24 Sep 2025 07:00:00 GMT",
      "label": "人件費・労働",
      "categories": [
        "labor"
      ]
    },
    {
      "title": "全国15,248件から見る、物価高・人手不足の時代、飲食店出店はどう変わったのか - PR TIMES",
      "link": "https://news.google.com/rss/articles/CBMiakFVX3lxTE1FNXM2c2l3UXF4bGIyWlE5eUZFSEt0WFRvZ1BaT2lkeEpVMmNvcHR0eW1ZQUNrTFNrbTc5RDdNWC1qWWVZYnd1ZVJGZFFORVEwd3lsUmw0eUFZWWVWSEkxNi1oRmdvSjhOcXc?oc=5",
      "summary": "全国15,248件から見る、物価高・人手不足の時代、飲食店出店はどう変わったのか  PR TIMES",
      "published": "Thu, 05 Feb 2026 08:00:00 GMT",
      "label": "人件費・労働",
      "categories": [
        "labor"
      ]
    },
    {
      "title": "飲食店の“人手不足倒産”を止める切り札…ロボットと冷凍テクノロジーで経営が激変 - ビジネスジャーナル",
      "link": "https://news.google.com/rss/articles/CBMiW0FVX3lxTE9mYnVETW9RUVRnbGIyM0t6OWVRd3h2SlhFQUFlMVY3QWRsekEweEZkVjVVM1RIOGhFd0NXaTVmRGU3azIxZTA4dGxTbDJLYVNwQVhxX0hVdjFPZnM?oc=5",
      "summary": "飲食店の“人手不足倒産”を止める切り札…ロボットと冷凍テクノロジーで経営が激変  ビジネスジャーナル",
      "published": "Thu, 04 Dec 2025 08:00:00 GMT",
      "label": "人件費・労働",
      "categories": [
        "labor"
      ]
    },
    {
      "title": "2025年度上期、飲食業界の平均給与が上昇。東京は月給30万円台へ | 飲食店ドットコム ジャーナル - 飲食店ドットコム",
      "link": "https://news.google.com/rss/articles/CBMiXEFVX3lxTE1oYTc2cDNCT2dGcWpMbXhteko0WUFvMGVXUUVNS0hadEJyMmlTQ0VnZkphcGpYN1d0alhIRFBhaU55Ym9palF2WDVRUkl1UnBaSHRlZktoSTRDWmhS?oc=5",
      "summary": "2025年度上期、飲食業界の平均給与が上昇。東京は月給30万円台へ | 飲食店ドットコム ジャーナル  飲食店ドットコム",
      "published": "Thu, 13 Nov 2025 08:00:00 GMT",
      "label": "人件費・労働",
      "categories": [
        "labor"
      ]
    },
    {
      "title": "人手不足の飲食店、時給の目安は最低賃金プラス何%？ - Forbes JAPAN",
      "link": "https://news.google.com/rss/articles/CBMiWEFVX3lxTE5yWDhWZmRlOGlya2RBZ0pqOHhKQms3SUNDdjdXdmRYYXNUZ0lFY0xFcGNoNEw3QmtPcnNsbU1iLUFMLWRKbG92Z2dZcW1Bb1hCZlE5RjNLYUI?oc=5",
      "summary": "人手不足の飲食店、時給の目安は最低賃金プラス何%？  Forbes JAPAN",
      "published": "Tue, 07 Jan 2025 08:00:00 GMT",
      "label": "人件費・労働",
      "categories": [
        "labor"
      ]
    },
    {
      "title": "いくらなら人が来ますか？「理想は1200円」 人材獲得競争が熾烈な飲食業界 最低賃金だけではアルバイトは来ない - TBS NEWS DIG",
      "link": "https://news.google.com/rss/articles/CBMiV0FVX3lxTE91bTBGR01lNGhiQmFsaVZ1a0RGTXpLd0o2VFhXS3NyVDVieTQ1NGxtR0VCS1B4eUdJclkxT2N2T2NXUmlfdjZNb0xiWnNfS0FuWDI5bWp6cw?oc=5",
      "summary": "いくらなら人が来ますか？「理想は1200円」 人材獲得競争が熾烈な飲食業界 最低賃金だけではアルバイトは来ない  TBS NEWS DIG",
      "published": "Thu, 03 Oct 2024 07:00:00 GMT",
      "label": "人件費・労働",
      "categories": [
        "labor"
      ]
    },
    {
      "title": "人手不足に対する企業の動向調査（2024年10月） - tdb.co.jp",
      "link": "https://news.google.com/rss/articles/CBMidkFVX3lxTFAybTdDOXVuWmhzUnJEZXhvZkJIMGFPaEdCUGVrSzJRWm1CYkFDMG1KMi1kQjNKWVRHWmladFpVZTFpcEpJbzJINlJJVHJwVjQzdzZJMVFBejQybmZTQUNsWWk3TTFpWUlkanFhNjMwaXE2T3lKcHc?oc=5",
      "summary": "人手不足に対する企業の動向調査（2024年10月）  tdb.co.jp",
      "published": "Wed, 13 Nov 2024 08:00:00 GMT",
      "label": "人件費・労働",
      "categories": [
        "labor"
      ]
    },
    {
      "title": "企業の人手不足を調査、正社員が足りない企業は半数超。飲食店、宿泊施設の不足率は緩和傾向に - やまとごころ.jp",
      "link": "https://news.google.com/rss/articles/CBMiXkFVX3lxTE5zYkRqUkpmcnZkMVlaMDJ3V3FHSjZtQW9DbTFLVDd0MTJBazEzSG5XdUxScWdvVFRsMGkwVm9qM3JraDRaS2VxUmhjLUtTdmwwd2lUWEVXSEEwdERFUkE?oc=5",
      "summary": "企業の人手不足を調査、正社員が足りない企業は半数超。飲食店、宿泊施設の不足率は緩和傾向に  やまとごころ.jp",
      "published": "Tue, 26 Nov 2024 08:00:00 GMT",
      "label": "人件費・労働",
      "categories": [
        "labor"
      ]
    },
    {
      "title": "「外国人客が明らかに減った」観光地の飲食店に広がる異変…中国客が半減超、訪日客減少で外食産業に迫る“空洞化”リスク - Yahoo!ニュース",
      "link": "https://news.google.com/rss/articles/CBMif0FVX3lxTE5zamtZekVFXzFfekpUTWNjY1JrUzJaVFJLamJISkFrSm51WkpYbFNjY3BhVnA2Q3pMVldPZjRkS1JtWW9zTkdjZWQ2ZkdFMS10YnFxd0FtcWd2bjJWUmVPaEx6WXNGQ0NPM3c4enB5N2FscWdzNGo0TWtqdUpITDA?oc=5",
      "summary": "「外国人客が明らかに減った」観光地の飲食店に広がる異変…中国客が半減超、訪日客減少で外食産業に迫る“空洞化”リスク  Yahoo!ニュース",
      "published": "Sat, 23 May 2026 07:00:00 GMT",
      "label": "外食・消費動向",
      "categories": [
        "consumer"
      ]
    },
    {
      "title": "食料品の消費税ゼロ、外食業界「客流れる」と不安 高市首相の答えは - 朝日新聞",
      "link": "https://news.google.com/rss/articles/CBMiZ0FVX3lxTFBkSmVDWHVRRnpOdk5VWk53blFZTnI5NkdoaEg5Z1dCMXlqRDNtc21VZS01bVgwZm05dXlPQ0pHZUx0MVJzRm85c1FIZmJ0SWZnTDdZWnlGYTBJUTdtYklMS3lVbnlCZVk?oc=5",
      "summary": "食料品の消費税ゼロ、外食業界「客流れる」と不安 高市首相の答えは  朝日新聞",
      "published": "Fri, 30 Jan 2026 08:00:00 GMT",
      "label": "外食・消費動向",
      "categories": [
        "consumer"
      ]
    },
    {
      "title": "餃子の王将&ココイチで客離れ進む衝撃…外食「1000円の壁」で分かれる明暗 - au Webポータル",
      "link": "https://news.google.com/rss/articles/CBMie0FVX3lxTE9WR2VsSi1QZXRmTktoT1E4NUVqM2dMU3VJV3hhZ245akJzajBFX1U5cF9ZUl9HNm5WV3Y3WTJWYWwzM2pYTDlBQ1pTMlN0V2l3VEpEcTF6MFo4by0ycFdXRDNhNERscFFXY01aRUM0US1DQTFIa09PN2pvOA?oc=5",
      "summary": "餃子の王将&ココイチで客離れ進む衝撃…外食「1000円の壁」で分かれる明暗  au Webポータル",
      "published": "Wed, 20 May 2026 21:55:00 GMT",
      "label": "外食・消費動向",
      "categories": [
        "consumer"
      ]
    },
    {
      "title": "「飲食店の客離れを招く」食料品の消費税減税に懸念表明 日本フードサービス協会 - TBS NEWS DIG",
      "link": "https://news.google.com/rss/articles/CBMidEFVX3lxTE9hdi1RcFZ6LW1lVUlSN21sUFhRY1ZQbGY5eFJBMng4blU4eW9ydWp0cEJzUi1VSjNUaHQxQmhpQ2xvVi1EckJEZm1UX2dEeDNBWWVWU25uSXhDWU42azhFNTRGMXg1NXFsQTRhZWE5WGtCa2Nj?oc=5",
      "summary": "「飲食店の客離れを招く」食料品の消費税減税に懸念表明 日本フードサービス協会  TBS NEWS DIG",
      "published": "Wed, 25 Feb 2026 08:00:00 GMT",
      "label": "外食・消費動向",
      "categories": [
        "consumer"
      ]
    },
    {
      "title": "外食業界「消費税ゼロ」に反対 来店客離れで経営に打撃 - 北海道新聞デジタル",
      "link": "https://news.google.com/rss/articles/CBMiWkFVX3lxTFBYWHJEMXYyYW1BcXQ4QXZkSUI4X1Z5eUZaZWNSaU1CNlUyeWV6UEN5eVljeUwtdGpoOE9xMlZjbTFJOS1najlIcU5zTDF6cTE3TEdoU0lqZXlUZw?oc=5",
      "summary": "外食業界「消費税ゼロ」に反対 来店客離れで経営に打撃  北海道新聞デジタル",
      "published": "Wed, 25 Feb 2026 08:00:00 GMT",
      "label": "外食・消費動向",
      "categories": [
        "consumer"
      ]
    },
    {
      "title": "外食 25年の全店売上高7.3％増 単価上昇が貢献、客数は頭打ち感も JF調査 - 食品新聞 WEB版",
      "link": "https://news.google.com/rss/articles/CBMiZEFVX3lxTE1xeUtYc3QwX1FrbjVPV3ZFS3dqcjJLdlVtNVV1QUJ6S0ZVVUhvdUNLb09kRTY4c3JyWHVyNC13QzI0UHVzNy1xVXhCcHh4eXpETFNyUlZLQzFabUJxOVR4OWQ3OVc?oc=5",
      "summary": "外食 25年の全店売上高7.3％増 単価上昇が貢献、客数は頭打ち感も JF調査  食品新聞 WEB版",
      "published": "Fri, 13 Feb 2026 08:00:00 GMT",
      "label": "外食・消費動向",
      "categories": [
        "consumer"
      ]
    },
    {
      "title": "外食業界「消費税ゼロ」に反対 来店客離れで経営に打撃 - nippon.com",
      "link": "https://news.google.com/rss/articles/CBMiY0FVX3lxTFA3TWpKdnVvUGVTVVhTc2RNb3ZZMWZGLXk4T1hnLU5lZXhySXB6cWdldVZGQmVkdjBKNElzZlk4Qzc3Y05hSGlVaGptSmZ1NEVNMkV6dklwREYyT1JZNXhPZHpHMA?oc=5",
      "summary": "外食業界「消費税ゼロ」に反対 来店客離れで経営に打撃  nippon.com",
      "published": "Wed, 25 Feb 2026 08:00:00 GMT",
      "label": "外食・消費動向",
      "categories": [
        "consumer"
      ]
    },
    {
      "title": "「食料品消費税ゼロになると客が来なくなる」居酒屋店が悲鳴…減税で分かれる業界の明暗 - スマートニュース",
      "link": "https://news.google.com/rss/articles/CBMi1wRBVV95cUxPeE1SMmpPbWdlcWpYUTJzZVp4V29JNU5POFRDTWtOTzFGVGZFX3lpMVhSR05mTDRXQUNyRUxnUXlTRWlybk1JUWN2c1FKOVhYSTYyNVM4MHpJRTZjSmRkMElvOGhadTBhSlh6Q2Y2Rk14Z2F6MEh4NlNaVWh5TVpFamc3a3Q5REJpZVJpYW5Dc0U2MnNwV3hEQ3VrT3lNWXJESGNhSVI2QkRkV2E1T2FEVXBnVGlPSWtNc2o3TzZOM2loS3dmaC1KZFNvU0hBcERiOG5ibmd4azVjWVV5QlpnV1lsRHRCSVdybDZCclpUR0x1M3JpLWkyeFcwN0JfeFNncnoxeFAzQkxUSlNKSkJVaXdDM2U2N3NFZEN3MFNLMlREUGQ3NkRJV0xaU20tVWp3cVJwRzROQWU5N2RKNDY0MkN3RHZZOUpNSXBROVJtNjZGZTFzRlhVdFBFWVYtVHc0VnpQcVBjbS12eG5OcUZwMExZaVRXVDgwaHZHLWZyMktUd08xamZGbUNMazFjZUl3MUlQVlhuVTJUWUNJRHQwbTJMYmVMWXRtQmNzM1VfU0R3XzVzR3VZOGFNRlFuQmpPazZma2J4T3B1MjBtRWk1ODNncFFOZDhOelZ4endQQmF2SUV6aGE0aGdyNDZ3NUtkVzlqbXRlNmVpNlIybUxkWHVKS2l5d3Z2WktXc3AweWtBUG4yMkhYMmsxOXdhdk9UZE1LdDViR2plRTJyZ3NpNGRuMWo5Q1l5RlVaUzlybW9XZ2I0WUJVY0lNSklhc3N5a213c0NCbw?oc=5",
      "summary": "「食料品消費税ゼロになると客が来なくなる」居酒屋店が悲鳴…減税で分かれる業界の明暗  スマートニュース",
      "published": "Sun, 01 Mar 2026 08:00:00 GMT",
      "label": "外食・消費動向",
      "categories": [
        "consumer"
      ]
    },
    {
      "title": "低価格路線のサイゼリヤは客数を増やしているが…外食を利用する消費者の財布が限界を超えつつある過酷な現実 - 東洋経済オンライン",
      "link": "https://news.google.com/rss/articles/CBMiX0FVX3lxTE5RQ0JWTmdxcEtiXzRKS2Y3b1RuYVBwSUNYVmVmZThNWjhjUFcwdlF5ZzdNVjNjNTBjS0tDTEp6b2tVS2xfZDBieGJyb242MjBfdVFIVFdmVndsMkM4MmJF?oc=5",
      "summary": "低価格路線のサイゼリヤは客数を増やしているが…外食を利用する消費者の財布が限界を超えつつある過酷な現実  東洋経済オンライン",
      "published": "Sat, 13 Sep 2025 07:00:00 GMT",
      "label": "外食・消費動向",
      "categories": [
        "consumer"
      ]
    },
    {
      "title": "外食業界「消費税ゼロ」に反対 - 京都新聞デジタル",
      "link": "https://news.google.com/rss/articles/CBMiW0FVX3lxTFB1MEVkZVNCUmo3RGc1VGhDVWVMUFh1aXhJWlRqXzdZeGhSMURaMHhDMHNkMzJoUUxnYTZOSk9Nc1pTbTl3NnpxM2I5VUZRbjNjdHBZbGJYVnE2TVE?oc=5",
      "summary": "外食業界「消費税ゼロ」に反対  京都新聞デジタル",
      "published": "Wed, 25 Feb 2026 08:00:00 GMT",
      "label": "外食・消費動向",
      "categories": [
        "consumer"
      ]
    },
    {
      "title": "「値上げできない」「客は来ない」 居酒屋が追い詰められる構造とは（山路力也） - エキスパート - Yahoo!ニュース",
      "link": "https://news.google.com/rss/articles/CBMiiAFBVV95cUxQakdxYkRPc2VoOG5FMDBMVm1GTWNVemRWbmNVZmZVQ3d1N0FKZm03alprd0g3T0oyYzBZY3JYQXItVE5SVlJOQkNSNnEwM2JLTzVPRDhJS0Y5SFphajhnS0FhSmlnQy1vNXhkcWFHZFFWcC1NNlJRMUI2SWZBVGR1SkxBSGdJRVlN?oc=5",
      "summary": "「値上げできない」「客は来ない」 居酒屋が追い詰められる構造とは（山路力也） - エキスパート  Yahoo!ニュース",
      "published": "Sat, 23 May 2026 05:46:41 GMT",
      "label": "ラーメン・飲食",
      "categories": [
        "restaurant"
      ]
    },
    {
      "title": "25年度のラーメン店倒産、過去2番目に多い57件 物価高で - 日本経済新聞",
      "link": "https://news.google.com/rss/articles/CBMibEFVX3lxTE9jMmY5N3g3ODBsVzBncmo5dmJwRGUyWmRvTDgtbzNXT055emN2TzE1dnFHVjU3R2Rybk50R1BXWnl1RE9fd2F5bjVMLUJCdnJBay0zVkc3RURzNGZ2UnNVMDNnZUxuOGhzZktRcw?oc=5",
      "summary": "25年度のラーメン店倒産、過去2番目に多い57件 物価高で  日本経済新聞",
      "published": "Wed, 08 Apr 2026 07:00:00 GMT",
      "label": "ラーメン・飲食",
      "categories": [
        "restaurant"
      ]
    },
    {
      "title": "4年ぶりにラーメン店倒産件数が減少…「値上げ」への理解が広まったことが要因 2026年は“ラーメン・コングロマリット化”進む可能性も - FNNプライムオンライン",
      "link": "https://news.google.com/rss/articles/CBMiTEFVX3lxTFBIdEhiU1E5X0xNa245bnJJRTdoNTR4a0hWNmd0ODRsdWFtS2RtVVdIcmE3em5yLUwtVENScm16TGZ4dmZuNUIyaEdoWWk?oc=5",
      "summary": "4年ぶりにラーメン店倒産件数が減少…「値上げ」への理解が広まったことが要因 2026年は“ラーメン・コングロマリット化”進む可能性も  FNNプライムオンライン",
      "published": "Sat, 10 Jan 2026 08:00:00 GMT",
      "label": "ラーメン・飲食",
      "categories": [
        "restaurant"
      ]
    },
    {
      "title": "2025年度の「ラーメン店」倒産は2番目 人手不足や値上げが影響 (2026年4月8日掲載) - ライブドアニュース",
      "link": "https://news.google.com/rss/articles/CBMiXkFVX3lxTFB3YldRMXlISEhWcnE3dm5QOWRLZS1mMGdXZ21yMTl4em8wMnZMQzdWcGRrTVhkOUtEMlBFNXNwOXZ3aW9FVTRVMDUtbW9mUGNYT2s0Q3JBSW5Fekptb3c?oc=5",
      "summary": "2025年度の「ラーメン店」倒産は2番目 人手不足や値上げが影響 (2026年4月8日掲載)  ライブドアニュース",
      "published": "Wed, 08 Apr 2026 07:00:00 GMT",
      "label": "ラーメン・飲食",
      "categories": [
        "restaurant"
      ]
    },
    {
      "title": "2025年の「焼肉店」倒産 46件 年間最多を更新 値上げ・高級化で客離れ加速、低価格チェーンとの競争激化 - 東京商工リサーチ",
      "link": "https://news.google.com/rss/articles/CBMiZkFVX3lxTE9XdmllSFJ6T1lKbS1sQmZrWTJXNjVTbnl6TVBuQnM1S19nZmVlS09Ra3lTVUluYTk2MzhHUjdRMjFGMjNjQ1N0U09BOTZncEVZb1NfMjJIQ0Y2V1Jyd2VDOFFRRnFIZw?oc=5",
      "summary": "2025年の「焼肉店」倒産 46件 年間最多を更新 値上げ・高級化で客離れ加速、低価格チェーンとの競争激化  東京商工リサーチ",
      "published": "Fri, 31 Oct 2025 07:00:00 GMT",
      "label": "ラーメン・飲食",
      "categories": [
        "restaurant"
      ]
    },
    {
      "title": "「町中華」の“息切れ倒産”が増加 ブームにも支えられ職人技で踏ん張ってきたが… 大手チェーンは値上げでも絶好調 - AERA DIGITAL",
      "link": "https://news.google.com/rss/articles/CBMiWkFVX3lxTE9VVk9iRDhxQV8ybVVLaTFDMUdGc2xHX0w5Y01HNEMyMUZEcXQ5SDJ4bWlhSE85Wms4NlJGRjBwNTZCWnRDVEQwaTR3LTRyeV95Rm1fOTdJOTA1UQ?oc=5",
      "summary": "「町中華」の“息切れ倒産”が増加 ブームにも支えられ職人技で踏ん張ってきたが… 大手チェーンは値上げでも絶好調  AERA DIGITAL",
      "published": "Wed, 19 Nov 2025 08:00:00 GMT",
      "label": "ラーメン・飲食",
      "categories": [
        "restaurant"
      ]
    },
    {
      "title": "「値上げすれば客離れ、しなければ倒産」 飲食店を追い詰める「価格転嫁率32.3%」の現実 #エキスパートトピ - Yahoo!ニュース",
      "link": "https://news.google.com/rss/articles/CBMiiAFBVV95cUxNeWN0ZW5qLV8wVXJVVlk2SHJBT1ZtT3lfLUR1NDQzZmwyRXI2LS1TUV9Odms2Qy1RTUZXcVVkb1VuUHdzZnVvd0JLbkpRUHktcldzSnhkalFidkhQVWM1WUJnS3IwbkxsTWVOcHA2OHdmZEhvLThFeHAwTTUyTTVCWFFoQTlQblhV?oc=5",
      "summary": "「値上げすれば客離れ、しなければ倒産」 飲食店を追い詰める「価格転嫁率32.3%」の現実 #エキスパートトピ  Yahoo!ニュース",
      "published": "Sat, 17 Jan 2026 08:00:00 GMT",
      "label": "ラーメン・飲食",
      "categories": [
        "restaurant"
      ]
    },
    {
      "title": "ラーメンチェーン『天下一品』、首都圏で閉店ラッシュ。原因はフランチャイズ離れか？ - 飲食店ドットコム",
      "link": "https://news.google.com/rss/articles/CBMiXEFVX3lxTFBveG1nRDdQUUFxbEg0TDdYdTZfRnBJWEZOdWUwU0VtSlprdmVFUEF4UmxaS2pGSk1lMmIzaFl1QldjMWlaeG92cWZ2VXdrXzJWUS1zV3hERmtsTFlz?oc=5",
      "summary": "ラーメンチェーン『天下一品』、首都圏で閉店ラッシュ。原因はフランチャイズ離れか？  飲食店ドットコム",
      "published": "Tue, 17 Jun 2025 07:00:00 GMT",
      "label": "ラーメン・飲食",
      "categories": [
        "restaurant"
      ]
    },
    {
      "title": "ラーメン店の倒産が過去最多：コスト増も「1000円の壁」に阻まれる - nippon.com",
      "link": "https://news.google.com/rss/articles/CBMiV0FVX3lxTE9YM0RRekZpSmlOcXFWRUdkOXl1RWlmQ3cwRjY0aERaenFKZDBDdVRDNlhlY2hKRjhPRGZzVEcySGsyc3RyV2gzZnZObk1oYXBYcVN5ZDlLaw?oc=5",
      "summary": "ラーメン店の倒産が過去最多：コスト増も「1000円の壁」に阻まれる  nippon.com",
      "published": "Tue, 11 Feb 2025 08:00:00 GMT",
      "label": "ラーメン・飲食",
      "categories": [
        "restaurant"
      ]
    },
    {
      "title": "「ラーメン店」の倒産、4年ぶり減少へ 「大淘汰時代」一服 2025年1-9月は46件発生、コスト高続くも「収益環境」に変化 - PR TIMES",
      "link": "https://news.google.com/rss/articles/CBMiakFVX3lxTE9RSG9FUG9CSnl5VXdHeERQbU5OX1duZmdzUDkxcHdRYmJPTlQzMzlobEVHSUEwZmpWclZFaDhwLTMwZ2daSnplNk04ZlBXVVQ3VnhndmNmMnRtNFQ5WUhwNG5oa0lja0ZtTHc?oc=5",
      "summary": "「ラーメン店」の倒産、4年ぶり減少へ 「大淘汰時代」一服 2025年1-9月は46件発生、コスト高続くも「収益環境」に変化  PR TIMES",
      "published": "Wed, 01 Oct 2025 07:00:00 GMT",
      "label": "ラーメン・飲食",
      "categories": [
        "restaurant"
      ]
    }
  ],
  "analysis": {
    "alert_level": "high",
    "headline": "コスト増と客単価維持の狭間で戦略再構築急務",
    "highlights": [
      {
        "tag": "【コスト】",
        "text": "中東情勢悪化によるナフサ高騰で、ビニール袋・トレー等の包装資材の仕入れ価格が30%上昇しています（数値不明、記事[30][33][34][39]）。鶏肉も鳥インフルエンザと中東情勢の影響で2003年の調査開始以来最高値に高騰中（数値不明、記事[31]）。キャベツの仕入れ価格は30円アップし、販売価格194円です（記事[38]）。円安は継続し、日銀が4月、5月に10兆円規模の為替介入を実施しましたが、輸入物価は2024年7月以来の伸びを示しており、国内物価への波及が必至です（記事[40][41][45]）。"
      },
      {
        "tag": "【人件費】",
        "text": "2025年度の最低賃金改定に向けた議論が始まっており、飲食業界の平均給与は2025年度上期に上昇し、東京では月給30万円台になる見込みです（記事[48][51]）。アルバイトの時給は最低賃金にプラスαが必要で、「理想は1200円」という声もあり、人材獲得競争が熾烈化しています（記事[52][53]）。企業の正社員人手不足は半数超ですが、飲食店・宿泊施設の人手不足率は緩和傾向にあるとの調査結果もあります（記事[54][55]）。"
      },
      {
        "tag": "【客数・消費】",
        "text": "観光地の飲食店では外国人客、特に中国客が半減超と「明らかに減った」という異変が生じています（記事[56]）。外食業界全体では2025年の全店売上高は7.3％増と予測されるものの、これは単価上昇によるもので客数は頭打ち感が指摘されています（記事[61]）。「餃子の王将」や「ココイチ」で客離れが見られ、外食の「1000円の壁」が顕在化していますが、低価格路線の「サイゼリヤ」は客数を増やしています（記事[58][64]）。また、食料品消費税ゼロ％の議論が外食業界内で来店客の内食化による客離れリスクとして懸念されています（記事[35][36][37][57][59][60][62][63][65]）。6月1日からの診療報酬改定により患者の窓口負担が増え、一般消費者の可処分所得が減少する可能性があります（記事[3]）。"
      },
      {
        "tag": "【競合・業界】",
        "text": "2025年度のラーメン店倒産は過去2番目に多い57件でしたが（記事[67][69][74]）、2025年1-9月期では46件と4年ぶりに減少傾向にあり、値上げへの消費者の理解が広まったことが要因と分析されています（記事[68][75]）。しかし、飲食店全体の価格転嫁率は32.3%に留まり、「値上げすれば客離れ、しなければ倒産」という厳しい現実が指摘されています（記事[72]）。ラーメンチェーン『天下一品』では首都圏で閉店ラッシュが発生しており、フランチャイズ離れが原因とされています（記事[73]）。焼肉店や町中華でも倒産が増加しており、特に町中華では大手チェーンが値上げしても好調な一方で“息切れ倒産”が増えています（記事[70][71]）。"
      },
      {
        "tag": "【世界情勢→経営】",
        "text": "中東情勢の悪化は、ナフサ価格の高騰を招き、ラーメンのテイクアウトや持ち帰り、仕入れ時の包装・保存に必須となるビニール袋やトレーといったプラスチック包装資材の仕入れコストを30%増加させています（記事[30][33][34][39]）。また、鳥インフルエンザと複合的に鶏肉の高騰にも影響しており（記事[31]）、ラーメンのトッピングやサイドメニューの原価を押し上げる可能性があります。"
      }
    ],
    "actions": [
      {
        "what": "テイクアウト用包装資材の仕入れ先を複数検討し、価格交渉または代替素材への切り替え可能性を調査する",
        "why": "中東情勢悪化でナフサ高騰によりビニール袋・トレーの仕入れが30%↑しているため（記事[30][33][34][39]）。",
        "when": "今週中"
      },
      {
        "what": "夏季限定の冷やしラーメンやつけ麺など、涼を感じるメニューの材料と原価を再計算し、今月中旬までに導入計画を策定する",
        "why": "東日本と北日本を中心に猛暑日が予想され、ラーメン離れの季節リスクがあるため（記事[2][29]）。",
        "when": "今月中"
      },
      {
        "what": "スタッフの時給を最低賃金+100円以上（例: 1200円以上）に引き上げるための費用対効果を試算し、求人広告に反映させる。同時に、ロボット導入などの省力化による生産性向上の可能性を調査する",
        "why": "2025年度の最低賃金引き上げ議論があり、飲食業界の平均給与上昇、人材獲得には理想1200円が目安という記事があるため（記事[48][51][52][53]）。ロボット・冷凍テクノロジーが人手不足倒産の切り札ともされているため（記事[50]）。",
        "when": "今週中"
      },
      {
        "what": "円安による輸入小麦、豚骨、醤油などの主要食材の価格変動リスクを再評価し、仕入れ先との長期契約や国産品への切り替え可能性について供給業者と協議する",
        "why": "円安が継続し、日銀の為替介入後も輸入物価が2024年7月以来の伸びを示しており、今後も主要食材のコスト上昇が予測されるため（記事[41][46]）。",
        "when": "今月中"
      },
      {
        "what": "食料品消費税ゼロ％が導入された場合のシミュレーションを行い、内食化による来店客数減少リスクと、テイクアウトや店内飲食の価格戦略について対策案を策定する",
        "why": "「食料品消費税ゼロ」の議論が活発であり、外食業界で客離れを招く懸念が示されているため（記事[36][57][59][60]）。",
        "when": "今月中"
      },
      {
        "what": "ラーメンの価格設定が「1000円の壁」に阻まれている現状を踏まえ、ラーメン一杯の顧客体験価値を高める工夫（例：限定メニュー、セット割引、サービス向上）を検討し、単価維持と客数確保の両立を目指す",
        "why": "大手チェーンで客離れが見られ、消費者の外食への財布が限界を超えつつある現実が指摘されているため（記事[58][64]）。",
        "when": "今月中"
      }
    ],
    "cost_items": [
      {
        "name": "包装資材（ビニール袋・トレー）",
        "direction": "上昇",
        "detail": "中東情勢悪化によるナフサ高騰で仕入れ価格30%↑（記事[30][33][34][39]）"
      },
      {
        "name": "鶏肉",
        "direction": "上昇",
        "detail": "鳥インフルエンザと中東情勢の影響で2003年の調査開始以来最高値（記事[31]）"
      },
      {
        "name": "キャベツ",
        "direction": "上昇",
        "detail": "仕入れ価格30円アップ（記事[38]）"
      },
      {
        "name": "輸入食材（小麦、豚骨、醤油など）",
        "direction": "上昇",
        "detail": "円安による輸入物価が2024年7月以来の伸び（記事[41][46]）"
      },
      {
        "name": "人件費",
        "direction": "上昇",
        "detail": "2025年度最低賃金改定議論、東京の飲食業界平均給与月給30万円台へ、アルバイト理想時給1200円（記事[48][51][53]）"
      }
    ],
    "relevant_indices": [
      1,
      2,
      3,
      5,
      17,
      24,
      25,
      29,
      30,
      31,
      32,
      33,
      34,
      35,
      36,
      37,
      38,
      39,
      40,
      41,
      42,
      43,
      44,
      45,
      46,
      47,
      48,
      49,
      50,
      51,
      52,
      53,
      54,
      55,
      56,
      57,
      58,
      59,
      60,
      61,
      62,
      63,
      64,
      65,
      66,
      67,
      68,
      69,
      70,
      71,
      72,
      73,
      74,
      75
    ]
  }
}